Laboratorio 6/ejercicio 6/ejercicio_6.v
module filp_flop(input clk, reset, D ,output reg Q);
  always @ (posedge clk, posedge reset) begin
    if (reset) begin
      Q <= 1'b0;
    end
    else begin
      Q <= D;
    end
  end
endmodule

module ejercicio_1(input wire clk, reset, A, B, output wire Y);

  wire D0, D1, Q0, Q1;

  assign D0 = (Q1 & B) | (Q0 & A & B);
  assign D1 = (~Q0 & Q1 & A);


  filp_flop a1(clk, reset, D0, Q0);
  filp_flop a2(clk, reset, D1, Q1);
  assign Y = Q0 & A & B;
endmodule

module ejercici_3(input wire clk, reset, boton, output wire Y1, Y2, Y3);

  wire D0, D1, D2, Q0, Q1, Q2;
  assign D2 = (~Q2 & Q1 & Q0 & boton) | (~Q2 & ~Q1 & ~Q0 & ~boton) | (Q2 & Q0 & ~boton) | (Q2 & ~Q1 & boton) | (Q2 & Q1 & ~Q0);
  assign D1 = ( Q1 & Q0 & ~boton) | ( Q1 & Q0 & boton ) | ( Q1 & Q0 & ~boton) | ( Q1 & ~Q0 & boton);
  assign D0 = ~Q0;

  filp_flop b0(clk, reset, D0, Q0);
  filp_flop b1(clk, reset, D1, Q1);
  filp_flop b2(clk, reset, D2, Q2);

  assign Y1 = Q2;
  assign Y2 = (~Q2 & Q1) | (Q2 & ~Q1);
  assign Y3 = (Q1 & ~Q0) | (Q1 & ~Q0);
endmodule

Laboratorio 6/ejercicio 6/ejercicio_6_tb.v
module testbench();

  reg clk, reset, A, B, boton;
  wire Y, Y1, Y2, Y3;

  ejercicio_1 l1(clk, reset, A, B, Y);
  ejercici_3  l2(clk, reset, boton, Y1, Y2, Y3);

  always
    #1 clk = ~clk;


initial begin
  $display(" A B | Y");
  $display("-------------------");
  $monitor("%b %b | %b", A, B, Y);
    clk = 0; reset = 0; A = 0; B = 0;
    #1 reset = 1;
    #1 reset = 0;
    #4 A = 0; B = 0;
    #8 A = 1; B = 0;
    #16 A = 0; B = 1;
    #32 A = 1; B = 1;
    #64 A = 0; B = 0;
end

initial begin
  #130
  $display("\n\n");
  $display(" Boton | Y1 Y2 Y3");
  $display("-------------------");
  $monitor("%b | %b %b %b", boton, Y1, Y2, Y3);
    clk = 0; reset = 0; boton = 0;
    #1 reset = 1;
    #1 reset = 0;
    #3 boton = 1;
    #6 boton = 1;
    #12 boton = 1;
    #24 boton = 1;
    #48 boton = 1;
    #96 boton = 1;
    #192 boton = 1;
    #384 boton = 1;
end
initial begin
  #900$finish;
end

initial begin
    $dumpfile("ejercicio6_tb.vcd");
    $dumpvars(0, testbench);
    end
endmodule

Laboratorio 6/ejercicio 6/ejercicio6_tb.vcd
$date
	Sat Sep 05 23:34:34 2020
$end
$version
	Icarus Verilog
$end
$timescale
	1ps
$end
$scope module testbench $end
$var wire 1 ! Y3 $end
$var wire 1 " Y2 $end
$var wire 1 # Y1 $end
$var wire 1 $ Y $end
$var reg 1 % A $end
$var reg 1 & B $end
$var reg 1 ' boton $end
$var reg 1 ( clk $end
$var reg 1 ) reset $end
$scope module l1 $end
$var wire 1 % A $end
$var wire 1 & B $end
$var wire 1 * D0 $end
$var wire 1 + D1 $end
$var wire 1 $ Y $end
$var wire 1 ( clk $end
$var wire 1 ) reset $end
$var wire 1 , Q1 $end
$var wire 1 - Q0 $end
$scope module a1 $end
$var wire 1 * D $end
$var wire 1 ( clk $end
$var wire 1 ) reset $end
$var reg 1 - Q $end
$upscope $end
$scope module a2 $end
$var wire 1 + D $end
$var wire 1 ( clk $end
$var wire 1 ) reset $end
$var reg 1 , Q $end
$upscope $end
$upscope $end
$scope module l2 $end
$var wire 1 . D0 $end
$var wire 1 / D1 $end
$var wire 1 0 D2 $end
$var wire 1 # Y1 $end
$var wire 1 " Y2 $end
$var wire 1 ! Y3 $end
$var wire 1 ' boton $end
$var wire 1 ( clk $end
$var wire 1 ) reset $end
$var wire 1 1 Q2 $end
$var wire 1 2 Q1 $end
$var wire 1 3 Q0 $end
$scope module b0 $end
$var wire 1 . D $end
$var wire 1 ( clk $end
$var wire 1 ) reset $end
$var reg 1 3 Q $end
$upscope $end
$scope module b1 $end
$var wire 1 / D $end
$var wire 1 ( clk $end
$var wire 1 ) reset $end
$var reg 1 2 Q $end
$upscope $end
$scope module b2 $end
$var wire 1 0 D $end
$var wire 1 ( clk $end
$var wire 1 ) reset $end
$var reg 1 1 Q $end
$upscope $end
$upscope $end
$upscope $end
$enddefinitions $end
#0
$dumpvars
x3
x2
x1
x0
x/
x.
x-
x,
0+
0*
0)
0(
x'
0&
0%
0$
x#
x"
x!
$end
#1
0/
0!
0"
1.
0-
0,
03
02
0#
01
1)
1(
#2
0)
0(
#3
x"
0.
x#
x1
13
1(
#4
0(
#5
1.
03
1(
#6
0(
#7
0.
13
1(
#8
0(
#9
1.
03
1(
#10
0(
#11
0.
13
1(
#12
0(
#13
1.
03
1(
#14
0(
1%
#15
0.
13
1(
#16
0(
#17
1.
03
1(
#18
0(
#19
0.
13
1(
#20
0(
#21
1.
03
1(
#22
0(
#23
0.
13
1(
#24
0(
#25
1.
03
1(
#26
0(
#27
0.
13
1(
#28
0(
#29
1.
03
1(
#30
0(
1&
0%
#31
0.
13
1(
#32
0(
#33
1.
03
1(
#34
0(
#35
0.
13
1(
#36
0(
#37
1.
03
1(
#38
0(
#39
0.
13
1(
#40
0(
#41
1.
03
1(
#42
0(
#43
0.
13
1(
#44
0(
#45
1.
03
1(
#46
0(
#47
0.
13
1(
#48
0(
#49
1.
03
1(
#50
0(
#51
0.
13
1(
#52
0(
#53
1.
03
1(
#54
0(
#55
0.
13
1(
#56
0(
#57
1.
03
1(
#58
0(
#59
0.
13
1(
#60
0(
#61
1.
03
1(
#62
0(
1%
#63
0.
13
1(
#64
0(
#65
1.
03
1(
#66
0(
#67
0.
13
1(
#68
0(
#69
1.
03
1(
#70
0(
#71
0.
13
1(
#72
0(
#73
1.
03
1(
#74
0(
#75
0.
13
1(
#76
0(
#77
1.
03
1(
#78
0(
#79
0.
13
1(
#80
0(
#81
1.
03
1(
#82
0(
#83
0.
13
1(
#84
0(
#85
1.
03
1(
#86
0(
#87
0.
13
1(
#88
0(
#89
1.
03
1(
#90
0(
#91
0.
13
1(
#92
0(
#93
1.
03
1(
#94
0(
#95
0.
13
1(
#96
0(
#97
1.
03
1(
#98
0(
#99
0.
13
1(
#100
0(
#101
1.
03
1(
#102
0(
#103
0.
13
1(
#104
0(
#105
1.
03
1(
#106
0(
#107
0.
13
1(
#108
0(
#109
1.
03
1(
#110
0(
#111
0.
13
1(
#112
0(
#113
1.
03
1(
#114
0(
#115
0.
13
1(
#116
0(
#117
1.
03
1(
#118
0(
#119
0.
13
1(
#120
0(
#121
1.
03
1(
#122
0(
#123
0.
13
1(
#124
0(
#125
1.
03
1(
#126
0(
0&
0%
#127
0.
13
1(
#128
0(
#129
1.
03
1(
#130
0.
13
0'
1(
#131
10
0"
1.
03
0#
01
0(
1)
#132
1"
0.
1#
11
13
1(
0)
#133
0(
#134
00
1.
03
1(
#135
10
0(
1'
#136
0.
13
1(
#137
0(
#138
1.
03
1(
#139
0(
#140
0.
13
1(
#141
0(
#142
1.
03
1(
#143
0(
#144
0.
13
1(
#145
0(
#146
1.
03
1(
#147
0(
#148
0.
13
1(
#149
0(
#150
1.
03
1(
#151
0(
#152
0.
13
1(
#153
0(
#154
1.
03
1(
#155
0(
#156
0.
13
1(
#157
0(
#158
1.
03
1(
#159
0(
#160
0.
13
1(
#161
0(
#162
1.
03
1(
#163
0(
#164
0.
13
1(
#165
0(
#166
1.
03
1(
#167
0(
#168
0.
13
1(
#169
0(
#170
1.
03
1(
#171
0(
#172
0.
13
1(
#173
0(
#174
1.
03
1(
#175
0(
#176
0.
13
1(
#177
0(
#178
1.
03
1(
#179
0(
#180
0.
13
1(
#181
0(
#182
1.
03
1(
#183
0(
#184
0.
13
1(
#185
0(
#186
1.
03
1(
#187
0(
#188
0.
13
1(
#189
0(
#190
1.
03
1(
#191
0(
#192
0.
13
1(
#193
0(
#194
1.
03
1(
#195
0(
#196
0.
13
1(
#197
0(
#198
1.
03
1(
#199
0(
#200
0.
13
1(
#201
0(
#202
1.
03
1(
#203
0(
#204
0.
13
1(
#205
0(
#206
1.
03
1(
#207
0(
#208
0.
13
1(
#209
0(
#210
1.
03
1(
#211
0(
#212
0.
13
1(
#213
0(
#214
1.
03
1(
#215
0(
#216
0.
13
1(
#217
0(
#218
1.
03
1(
#219
0(
#220
0.
13
1(
#221
0(
#222
1.
03
1(
#223
0(
#224
0.
13
1(
#225
0(
#226
1.
03
1(
#227
0(
#228
0.
13
1(
#229
0(
#230
1.
03
1(
#231
0(
#232
0.
13
1(
#233
0(
#234
1.
03
1(
#235
0(
#236
0.
13
1(
#237
0(
#238
1.
03
1(
#239
0(
#240
0.
13
1(
#241
0(
#242
1.
03
1(
#243
0(
#244
0.
13
1(
#245
0(
#246
1.
03
1(
#247
0(
#248
0.
13
1(
#249
0(
#250
1.
03
1(
#251
0(
#252
0.
13
1(
#253
0(
#254
1.
03
1(
#255
0(
#256
0.
13
1(
#257
0(
#258
1.
03
1(
#259
0(
#260
0.
13
1(
#261
0(
#262
1.
03
1(
#263
0(
#264
0.
13
1(
#265
0(
#266
1.
03
1(
#267
0(
#268
0.
13
1(
#269
0(
#270
1.
03
1(
#271
0(
#272
0.
13
1(
#273
0(
#274
1.
03
1(
#275
0(
#276
0.
13
1(
#277
0(
#278
1.
03
1(
#279
0(
#280
0.
13
1(
#281
0(
#282
1.
03
1(
#283
0(
#284
0.
13
1(
#285
0(
#286
1.
03
1(
#287
0(
#288
0.
13
1(
#289
0(
#290
1.
03
1(
#291
0(
#292
0.
13
1(
#293
0(
#294
1.
03
1(
#295
0(
#296
0.
13
1(
#297
0(
#298
1.
03
1(
#299
0(
#300
0.
13
1(
#301
0(
#302
1.
03
1(
#303
0(
#304
0.
13
1(
#305
0(
#306
1.
03
1(
#307
0(
#308
0.
13
1(
#309
0(
#310
1.
03
1(
#311
0(
#312
0.
13
1(
#313
0(
#314
1.
03
1(
#315
0(
#316
0.
13
1(
#317
0(
#318
1.
03
1(
#319
0(
#320
0.
13
1(
#321
0(
#322
1.
03
1(
#323
0(
#324
0.
13
1(
#325
0(
#326
1.
03
1(
#327
0(
#328
0.
13
1(
#329
0(
#330
1.
03
1(
#331
0(
#332
0.
13
1(
#333
0(
#334
1.
03
1(
#335
0(
#336
0.
13
1(
#337
0(
#338
1.
03
1(
#339
0(
#340
0.
13
1(
#341
0(
#342
1.
03
1(
#343
0(
#344
0.
13
1(
#345
0(
#346
1.
03
1(
#347
0(
#348
0.
13
1(
#349
0(
#350
1.
03
1(
#351
0(
#352
0.
13
1(
#353
0(
#354
1.
03
1(
#355
0(
#356
0.
13
1(
#357
0(
#358
1.
03
1(
#359
0(
#360
0.
13
1(
#361
0(
#362
1.
03
1(
#363
0(
#364
0.
13
1(
#365
0(
#366
1.
03
1(
#367
0(
#368
0.
13
1(
#369
0(
#370
1.
03
1(
#371
0(
#372
0.
13
1(
#373
0(
#374
1.
03
1(
#375
0(
#376
0.
13
1(
#377
0(
#378
1.
03
1(
#379
0(
#380
0.
13
1(
#381
0(
#382
1.
03
1(
#383
0(
#384
0.
13
1(
#385
0(
#386
1.
03
1(
#387
0(
#388
0.
13
1(
#389
0(
#390
1.
03
1(
#391
0(
#392
0.
13
1(
#393
0(
#394
1.
03
1(
#395
0(
#396
0.
13
1(
#397
0(
#398
1.
03
1(
#399
0(
#400
0.
13
1(
#401
0(
#402
1.
03
1(
#403
0(
#404
0.
13
1(
#405
0(
#406
1.
03
1(
#407
0(
#408
0.
13
1(
#409
0(
#410
1.
03
1(
#411
0(
#412
0.
13
1(
#413
0(
#414
1.
03
1(
#415
0(
#416
0.
13
1(
#417
0(
#418
1.
03
1(
#419
0(
#420
0.
13
1(
#421
0(
#422
1.
03
1(
#423
0(
#424
0.
13
1(
#425
0(
#426
1.
03
1(
#427
0(
#428
0.
13
1(
#429
0(
#430
1.
03
1(
#431
0(
#432
0.
13
1(
#433
0(
#434
1.
03
1(
#435
0(
#436
0.
13
1(
#437
0(
#438
1.
03
1(
#439
0(
#440
0.
13
1(
#441
0(
#442
1.
03
1(
#443
0(
#444
0.
13
1(
#445
0(
#446
1.
03
1(
#447
0(
#448
0.
13
1(
#449
0(
#450
1.
03
1(
#451
0(
#452
0.
13
1(
#453
0(
#454
1.
03
1(
#455
0(
#456
0.
13
1(
#457
0(
#458
1.
03
1(
#459
0(
#460
0.
13
1(
#461
0(
#462
1.
03
1(
#463
0(
#464
0.
13
1(
#465
0(
#466
1.
03
1(
#467
0(
#468
0.
13
1(
#469
0(
#470
1.
03
1(
#471
0(
#472
0.
13
1(
#473
0(
#474
1.
03
1(
#475
0(
#476
0.
13
1(
#477
0(
#478
1.
03
1(
#479
0(
#480
0.
13
1(
#481
0(
#482
1.
03
1(
#483
0(
#484
0.
13
1(
#485
0(
#486
1.
03
1(
#487
0(
#488
0.
13
1(
#489
0(
#490
1.
03
1(
#491
0(
#492
0.
13
1(
#493
0(
#494
1.
03
1(
#495
0(
#496
0.
13
1(
#497
0(
#498
1.
03
1(
#499
0(
#500
0.
13
1(
#501
0(
#502
1.
03
1(
#503
0(
#504
0.
13
1(
#505
0(
#506
1.
03
1(
#507
0(
#508
0.
13
1(
#509
0(
#510
1.
03
1(
#511
0(
#512
0.
13
1(
#513
0(
#514
1.
03
1(
#515
0(
#516
0.
13
1(
#517
0(
#518
1.
03
1(
#519
0(
#520
0.
13
1(
#521
0(
#522
1.
03
1(
#523
0(
#524
0.
13
1(
#525
0(
#526
1.
03
1(
#527
0(
#528
0.
13
1(
#529
0(
#530
1.
03
1(
#531
0(
#532
0.
13
1(
#533
0(
#534
1.
03
1(
#535
0(
#536
0.
13
1(
#537
0(
#538
1.
03
1(
#539
0(
#540
0.
13
1(
#541
0(
#542
1.
03
1(
#543
0(
#544
0.
13
1(
#545
0(
#546
1.
03
1(
#547
0(
#548
0.
13
1(
#549
0(
#550
1.
03
1(
#551
0(
#552
0.
13
1(
#553
0(
#554
1.
03
1(
#555
0(
#556
0.
13
1(
#557
0(
#558
1.
03
1(
#559
0(
#560
0.
13
1(
#561
0(
#562
1.
03
1(
#563
0(
#564
0.
13
1(
#565
0(
#566
1.
03
1(
#567
0(
#568
0.
13
1(
#569
0(
#570
1.
03
1(
#571
0(
#572
0.
13
1(
#573
0(
#574
1.
03
1(
#575
0(
#576
0.
13
1(
#577
0(
#578
1.
03
1(
#579
0(
#580
0.
13
1(
#581
0(
#582
1.
03
1(
#583
0(
#584
0.
13
1(
#585
0(
#586
1.
03
1(
#587
0(
#588
0.
13
1(
#589
0(
#590
1.
03
1(
#591
0(
#592
0.
13
1(
#593
0(
#594
1.
03
1(
#595
0(
#596
0.
13
1(
#597
0(
#598
1.
03
1(
#599
0(
#600
0.
13
1(
#601
0(
#602
1.
03
1(
#603
0(
#604
0.
13
1(
#605
0(
#606
1.
03
1(
#607
0(
#608
0.
13
1(
#609
0(
#610
1.
03
1(
#611
0(
#612
0.
13
1(
#613
0(
#614
1.
03
1(
#615
0(
#616
0.
13
1(
#617
0(
#618
1.
03
1(
#619
0(
#620
0.
13
1(
#621
0(
#622
1.
03
1(
#623
0(
#624
0.
13
1(
#625
0(
#626
1.
03
1(
#627
0(
#628
0.
13
1(
#629
0(
#630
1.
03
1(
#631
0(
#632
0.
13
1(
#633
0(
#634
1.
03
1(
#635
0(
#636
0.
13
1(
#637
0(
#638
1.
03
1(
#639
0(
#640
0.
13
1(
#641
0(
#642
1.
03
1(
#643
0(
#644
0.
13
1(
#645
0(
#646
1.
03
1(
#647
0(
#648
0.
13
1(
#649
0(
#650
1.
03
1(
#651
0(
#652
0.
13
1(
#653
0(
#654
1.
03
1(
#655
0(
#656
0.
13
1(
#657
0(
#658
1.
03
1(
#659
0(
#660
0.
13
1(
#661
0(
#662
1.
03
1(
#663
0(
#664
0.
13
1(
#665
0(
#666
1.
03
1(
#667
0(
#668
0.
13
1(
#669
0(
#670
1.
03
1(
#671
0(
#672
0.
13
1(
#673
0(
#674
1.
03
1(
#675
0(
#676
0.
13
1(
#677
0(
#678
1.
03
1(
#679
0(
#680
0.
13
1(
#681
0(
#682
1.
03
1(
#683
0(
#684
0.
13
1(
#685
0(
#686
1.
03
1(
#687
0(
#688
0.
13
1(
#689
0(
#690
1.
03
1(
#691
0(
#692
0.
13
1(
#693
0(
#694
1.
03
1(
#695
0(
#696
0.
13
1(
#697
0(
#698
1.
03
1(
#699
0(
#700
0.
13
1(
#701
0(
#702
1.
03
1(
#703
0(
#704
0.
13
1(
#705
0(
#706
1.
03
1(
#707
0(
#708
0.
13
1(
#709
0(
#710
1.
03
1(
#711
0(
#712
0.
13
1(
#713
0(
#714
1.
03
1(
#715
0(
#716
0.
13
1(
#717
0(
#718
1.
03
1(
#719
0(
#720
0.
13
1(
#721
0(
#722
1.
03
1(
#723
0(
#724
0.
13
1(
#725
0(
#726
1.
03
1(
#727
0(
#728
0.
13
1(
#729
0(
#730
1.
03
1(
#731
0(
#732
0.
13
1(
#733
0(
#734
1.
03
1(
#735
0(
#736
0.
13
1(
#737
0(
#738
1.
03
1(
#739
0(
#740
0.
13
1(
#741
0(
#742
1.
03
1(
#743
0(
#744
0.
13
1(
#745
0(
#746
1.
03
1(
#747
0(
#748
0.
13
1(
#749
0(
#750
1.
03
1(
#751
0(
#752
0.
13
1(
#753
0(
#754
1.
03
1(
#755
0(
#756
0.
13
1(
#757
0(
#758
1.
03
1(
#759
0(
#760
0.
13
1(
#761
0(
#762
1.
03
1(
#763
0(
#764
0.
13
1(
#765
0(
#766
1.
03
1(
#767
0(
#768
0.
13
1(
#769
0(
#770
1.
03
1(
#771
0(
#772
0.
13
1(
#773
0(
#774
1.
03
1(
#775
0(
#776
0.
13
1(
#777
0(
#778
1.
03
1(
#779
0(
#780
0.
13
1(
#781
0(
#782
1.
03
1(
#783
0(
#784
0.
13
1(
#785
0(
#786
1.
03
1(
#787
0(
#788
0.
13
1(
#789
0(
#790
1.
03
1(
#791
0(
#792
0.
13
1(
#793
0(
#794
1.
03
1(
#795
0(
#796
0.
13
1(
#797
0(
#798
1.
03
1(
#799
0(
#800
0.
13
1(
#801
0(
#802
1.
03
1(
#803
0(
#804
0.
13
1(
#805
0(
#806
1.
03
1(
#807
0(
#808
0.
13
1(
#809
0(
#810
1.
03
1(
#811
0(
#812
0.
13
1(
#813
0(
#814
1.
03
1(
#815
0(
#816
0.
13
1(
#817
0(
#818
1.
03
1(
#819
0(
#820
0.
13
1(
#821
0(
#822
1.
03
1(
#823
0(
#824
0.
13
1(
#825
0(
#826
1.
03
1(
#827
0(
#828
0.
13
1(
#829
0(
#830
1.
03
1(
#831
0(
#832
0.
13
1(
#833
0(
#834
1.
03
1(
#835
0(
#836
0.
13
1(
#837
0(
#838
1.
03
1(
#839
0(
#840
0.
13
1(
#841
0(
#842
1.
03
1(
#843
0(
#844
0.
13
1(
#845
0(
#846
1.
03
1(
#847
0(
#848
0.
13
1(
#849
0(
#850
1.
03
1(
#851
0(
#852
0.
13
1(
#853
0(
#854
1.
03
1(
#855
0(
#856
0.
13
1(
#857
0(
#858
1.
03
1(
#859
0(
#860
0.
13
1(
#861
0(
#862
1.
03
1(
#863
0(
#864
0.
13
1(
#865
0(
#866
1.
03
1(
#867
0(
#868
0.
13
1(
#869
0(
#870
1.
03
1(
#871
0(
#872
0.
13
1(
#873
0(
#874
1.
03
1(
#875
0(
#876
0.
13
1(
#877
0(
#878
1.
03
1(
#879
0(
#880
0.
13
1(
#881
0(
#882
1.
03
1(
#883
0(
#884
0.
13
1(
#885
0(
#886
1.
03
1(
#887
0(
#888
0.
13
1(
#889
0(
#890
1.
03
1(
#891
0(
#892
0.
13
1(
#893
0(
#894
1.
03
1(
#895
0(
#896
0.
13
1(
#897
0(
#898
1.
03
1(
#899
0(
#900
0.
13
1(
