laboratorio 9/Ejercicio 2/FLIPFLOPT.v
module flipflop(input clk, reset,En, D, output reg Q);
  always @ (posedge clk, posedge reset)
    if (reset)
      Q <= 1'b0;
    else if (En)
      Q <= D;
endmodule

module FLIPT(input clk, reset, En, output Q);

  wire clb;

  assign clb = ~Q;

  flipflop c(clk, reset, En, clb, Q);

endmodule

laboratorio 9/Ejercicio 2/FLIPFLOPT_tb.v
module testbench();

reg clk, reset, En;
wire Q;

FLIPT b(clk, reset, En, Q);

always
  #1 clk = ~clk;

initial begin
  #1
  $display("| Q |");
  $display("-----");
  $monitor("| %b |", Q);
     clk = 0; reset = 0; En = 1;
  #1 reset = 1; En = 1;
  #1 reset = 0; En = 1;
end

  initial
    #25 $finish;

  initial begin
    $dumpfile("FLIPFLOPT_tb.vcd");
    $dumpvars(0, testbench);
  end
  endmodule //testbench

laboratorio 9/Ejercicio 2/FLIPFLOPT_tb.vcd
$date
	Fri Oct 30 23:05:51 2020
$end
$version
	Icarus Verilog
$end
$timescale
	1ps
$end
$scope module testbench $end
$var wire 1 ! Q $end
$var reg 1 " En $end
$var reg 1 # clk $end
$var reg 1 $ reset $end
$scope module b $end
$var wire 1 " En $end
$var wire 1 % clb $end
$var wire 1 # clk $end
$var wire 1 $ reset $end
$var wire 1 ! Q $end
$scope module c $end
$var wire 1 % D $end
$var wire 1 " En $end
$var wire 1 # clk $end
$var wire 1 $ reset $end
$var reg 1 ! Q $end
$upscope $end
$upscope $end
$upscope $end
$enddefinitions $end
#0
$dumpvars
x%
x$
x#
x"
x!
$end
#1
1"
0$
0#
#2
1%
0!
1$
1#
#3
0$
0#
#4
0%
1!
1#
#5
0#
#6
1%
0!
1#
#7
0#
#8
0%
1!
1#
#9
0#
#10
1%
0!
1#
#11
0#
#12
0%
1!
1#
#13
0#
#14
1%
0!
1#
#15
0#
#16
0%
1!
1#
#17
0#
#18
1%
0!
1#
#19
0#
#20
0%
1!
1#
#21
0#
#22
1%
0!
1#
#23
0#
#24
0%
1!
1#
