laboratorio 10/Ejercicio 1/bloque1.v
module flip_flop4(input clk, reset,En, input [3:0]D, output reg [3:0]Q);
  always @ (posedge clk or posedge reset)begin
    if (reset)
      Q <= 4'b0;
    else if (En)
      Q <= D;
  end
endmodule

module fetch(input clk, reset,En, input [7:0]D, output [3:0]instr, oprnd);

 flip_flop4 b1(clk, reset, En, D[7:4], instr);
 flip_flop4 b2(clk, reset, En, D[3:0], oprnd);

endmodule

module contador(input wire clk,reset,En,load,
input wire [11:0]load2,
output reg [11:0]q);

always @(posedge clk or posedge reset or load or load2) begin
  if(reset)
  q <= 12'b000000000000;
  else if(load)
  q <= load2;
  else if(En)
  q <= q + 1;
  end
endmodule




module memoriaROM(input wire [11:0]localidad, output wire [7:0]respuesta);

reg [7:0] cerebro [0:4095];

  initial begin
    $readmemb("memory.list", cerebro);
  end

assign respuesta = cerebro[localidad];

endmodule



module EJERCICIO1(input clk, reset, En1, En2, load,
  input [11:0]D, output [7:0]Program_byte, output [3:0]instr, oprnd);

  wire [11:0]PC;

  contador a1( clk, reset, En1, load, D , PC);
  memoriaROM a2(PC, Program_byte);
  fetch a3(clk, reset, En2, Program_byte, instr, oprnd);

endmodule

laboratorio 10/Ejercicio 1/bloque1_tb.v
module testbench();

reg clk, reset, En1, En2, load;
reg [11:0]D;
wire [7:0]Program_byte;
wire [3:0]instr, oprnd;

EJERCICIO1 a1(clk, reset, En1, En2, load, D, Program_byte, instr, oprnd);

  always
    begin
    #1 clk = ~clk;
  end

  initial begin
  #1
  $display("---------------------------------------|----------------------------|");
  $display(" clk reset En1 En2  load         D      |  Program_byte instr oprnd  |");
  $display("---------------------------------------|----------------------------|");
  $monitor("%b    %b    %b    %b     %b    %b |    %b   %b   %b  |", clk, reset, En1, En2, load, D, Program_byte, instr, oprnd);
     clk = 0; reset = 0; En1 = 0; En2 = 0; D = 12'b000000000000; load = 0;
  #1 reset = 1; En1 = 0; En2 = 0;
  #1 reset = 0; En1 = 1; En2 = 1;
  #1 reset = 0; En1 = 1; En2 = 1;
  #1 reset = 0; En1 = 1; En2 = 1;
  #1 reset = 0; En1 = 1; En2 = 1;
  #1 reset = 0; En1 = 1; En2 = 1; load = 1; D = 12'b000000000100;
  #1 reset = 0; En1 = 1; En2 = 1; load = 0; D = 12'b000000000000;
  #1 reset = 0; En1 = 1; En2 = 1; load = 0; D = 12'b000000000000;
  #1 reset = 0; En1 = 1; En2 = 1; load = 0; D = 12'b000000000000;
  #1 reset = 0; En1 = 0; En2 = 0; load = 0; D = 12'b000000000000;
  #1 reset = 0; En1 = 0; En2 = 0; load = 0; D = 12'b000000000000;
  #1 reset = 0; En1 = 0; En2 = 0; load = 0; D = 12'b000000000000;


  end

  initial
   #14 $finish;

  initial begin
    $dumpfile("bloque1_tb.vcd");
    $dumpvars(0, testbench);
  end


endmodule

laboratorio 10/Ejercicio 1/bloque1_tb.vcd
$date
	Sat Nov 07 00:43:11 2020
$end
$version
	Icarus Verilog
$end
$timescale
	1ps
$end
$scope module testbench $end
$var wire 4 ! oprnd [3:0] $end
$var wire 4 " instr [3:0] $end
$var wire 8 # Program_byte [7:0] $end
$var reg 12 $ D [11:0] $end
$var reg 1 % En1 $end
$var reg 1 & En2 $end
$var reg 1 ' clk $end
$var reg 1 ( load $end
$var reg 1 ) reset $end
$scope module a1 $end
$var wire 12 * D [11:0] $end
$var wire 1 % En1 $end
$var wire 1 & En2 $end
$var wire 1 ' clk $end
$var wire 1 ( load $end
$var wire 1 ) reset $end
$var wire 4 + oprnd [3:0] $end
$var wire 4 , instr [3:0] $end
$var wire 8 - Program_byte [7:0] $end
$var wire 12 . PC [11:0] $end
$scope module a1 $end
$var wire 1 % En $end
$var wire 1 ' clk $end
$var wire 1 ( load $end
$var wire 12 / load2 [11:0] $end
$var wire 1 ) reset $end
$var reg 12 0 q [11:0] $end
$upscope $end
$scope module a2 $end
$var wire 12 1 localidad [11:0] $end
$var wire 8 2 respuesta [7:0] $end
$upscope $end
$scope module a3 $end
$var wire 8 3 D [7:0] $end
$var wire 1 & En $end
$var wire 1 ' clk $end
$var wire 1 ) reset $end
$var wire 4 4 oprnd [3:0] $end
$var wire 4 5 instr [3:0] $end
$scope module b1 $end
$var wire 4 6 D [3:0] $end
$var wire 1 & En $end
$var wire 1 ' clk $end
$var wire 1 ) reset $end
$var reg 4 7 Q [3:0] $end
$upscope $end
$scope module b2 $end
$var wire 4 8 D [3:0] $end
$var wire 1 & En $end
$var wire 1 ' clk $end
$var wire 1 ) reset $end
$var reg 4 9 Q [3:0] $end
$upscope $end
$upscope $end
$upscope $end
$upscope $end
$enddefinitions $end
#0
$dumpvars
bx 9
bx 8
bx 7
bx 6
bx 5
bx 4
bx 3
bx 2
bx 1
bx 0
bx /
bx .
bx -
bx ,
bx +
bx *
x)
x(
x'
x&
x%
bx $
bx #
bx "
bx !
$end
#1
0(
b0 $
b0 *
b0 /
0&
0%
0)
0'
#2
b100 6
b1000 8
b1001000 #
b1001000 -
b1001000 2
b1001000 3
b0 .
b0 0
b0 1
b0 "
b0 ,
b0 5
b0 7
b0 !
b0 +
b0 4
b0 9
1)
1'
#3
1&
1%
0)
0'
#4
b0 8
b1000000 #
b1000000 -
b1000000 2
b1000000 3
b1 .
b1 0
b1 1
b1000 !
b1000 +
b1000 4
b1000 9
b100 "
b100 ,
b100 5
b100 7
1'
#5
0'
#6
b101 6
b1111 8
b1011111 #
b1011111 -
b1011111 2
b1011111 3
b10 .
b10 0
b10 1
b0 !
b0 +
b0 4
b0 9
1'
#7
b1 8
b1010001 #
b1010001 -
b1010001 2
b1010001 3
b100 .
b100 0
b100 1
b100 $
b100 *
b100 /
1(
0'
#8
b0 6
b1010 8
b1010 #
b1010 -
b1010 2
b1010 3
b101 .
b101 0
b101 1
b1 !
b1 +
b1 4
b1 9
b101 "
b101 ,
b101 5
b101 7
b0 $
b0 *
b0 /
0(
1'
#9
0'
#10
b1 6
b1 8
b10001 #
b10001 -
b10001 2
b10001 3
b110 .
b110 0
b110 1
b0 "
b0 ,
b0 5
b0 7
b1010 !
b1010 +
b1010 4
b1010 9
1'
#11
0&
0%
0'
