laboratorio 9/Ejercicio 3/FLIPFLOPJK.v
module flipflop(input clk, reset,En, D, output reg Q);
  always @ (posedge clk or posedge reset) begin
    if (reset)
      Q <= 1'b0;
    else if (En)
      Q <= D;
  end
endmodule

module FLIPFLOPJK(input clk, reset, En, J, K, output Q);

wire nQ, nK, A1, A2, d;

not(nQ, Q);
not(nK, K);

and(A1, nK, Q);
and(A2, J, nQ);

or(d, A1, A2);

flipflop a(clk, reset, En, d, Q);

endmodule

laboratorio 9/Ejercicio 3/FLIPFLOPJK_tb.v
module testbench();
  reg clk, reset, En, J, K;
  wire Q;

  FLIPFLOPJK g(clk, reset, En, J, K, Q);

  always
    begin
    #1 clk = ~clk;
  end

  initial begin
    #1
    $display("| Clk reset En J K | Q |");
    $display("-------------------------");
    $monitor("| %b     %b   %b  %b %b | %b |", clk, reset, En, J, K, Q);
       clk = 0; reset = 0; En = 0; J = 0; K = 0;
    #2 reset = 1; En = 0; J = 0; K = 0;
    #2 reset = 0; En = 1; J = 0; K = 0;
    #2 En = 1; J = 1; K = 0;
    #2 En = 1; J = 0; K = 1;
    #2 En = 1; J = 1; K = 1;
    #2 En = 0; J = 0; K = 0;
    #2 En = 0; J = 0; K = 1;
    #2 En = 0; J = 1; K = 0;
  end

    initial
      #25 $finish;

    initial begin
      $dumpfile("FLIPFLOPJK_tb.vcd");
      $dumpvars(0, testbench);
    end

endmodule //testbenc

laboratorio 9/Ejercicio 3/FLIPFLOPJK_tb.vcd
$date
	Sat Oct 31 00:16:30 2020
$end
$version
	Icarus Verilog
$end
$timescale
	1ps
$end
$scope module testbench $end
$var wire 1 ! Q $end
$var reg 1 " En $end
$var reg 1 # J $end
$var reg 1 $ K $end
$var reg 1 % clk $end
$var reg 1 & reset $end
$scope module g $end
$var wire 1 ' A1 $end
$var wire 1 ( A2 $end
$var wire 1 " En $end
$var wire 1 # J $end
$var wire 1 $ K $end
$var wire 1 % clk $end
$var wire 1 ) d $end
$var wire 1 * nK $end
$var wire 1 + nQ $end
$var wire 1 & reset $end
$var wire 1 ! Q $end
$scope module a $end
$var wire 1 ) D $end
$var wire 1 " En $end
$var wire 1 % clk $end
$var wire 1 & reset $end
$var reg 1 ! Q $end
$upscope $end
$upscope $end
$upscope $end
$enddefinitions $end
#0
$dumpvars
x+
x*
x)
x(
x'
x&
x%
x$
x#
x"
x!
$end
#1
1*
0(
0$
0#
0"
0&
0%
#2
1%
#3
0)
0'
1+
0!
0%
1&
#4
1%
#5
0%
1"
0&
#6
1%
#7
1)
1(
0%
1#
#8
0(
1'
0+
1!
1%
#9
0)
0'
0*
0%
1$
0#
#10
1+
0!
1%
#11
1)
1(
0%
1#
#12
0)
0(
0+
1!
1%
#13
1)
1'
1*
0%
0$
0#
0"
#14
1%
#15
0)
0'
0*
0%
1$
#16
1%
#17
1)
1'
1*
0%
0$
1#
