laboratorio 9/Ejercicio 1/FLIP-FLOP-D-2/FLIPFLOP2.v
module flip_flop(input clk, reset,En, D, output reg Q);
  always @ (posedge clk or posedge reset)begin
    if (reset)
      Q <= 1'b0;
    else if (En)
      Q <= D;
  end
endmodule



module flip_flop_2(input clk, reset, En, input wire [1:0]D, output [1:0]Q);

  flip_flop a(clk, reset, En, D[1], Q[1]);
  flip_flop a1(clk, reset, En, D[0], Q[0]);

endmodule

laboratorio 9/Ejercicio 1/FLIP-FLOP-D-2/FLIPFLOP2_tb.v
module testbench ();

  reg clk, reset, En;
  reg [1:0]D;
  wire [1:0]Q;

  flip_flop_2 b(clk, reset, En, D, Q);

  always
  #1 clk = ~clk;

  initial begin
    #1
    $display("|clk reset En  D | Q |");
    $display("-------------------");
    $monitor("|  %b   %b   %b  %b | %b |",clk, reset, En, D, Q);
      clk = 0; reset = 0; En = 0; D = 2'b00;
    #1 reset = 1; En = 0; D = 2'b00;
    #1 reset = 0; En = 1; D = 2'b01;
    #1 reset = 0; En = 1; D = 2'b10;
    #1 reset = 0; En = 1; D = 2'b10;
    #1 reset = 0; En = 1; D = 2'b10;
    #1 reset = 0; En = 1; D = 2'b11;
    #1 reset = 0; En = 1; D = 2'b11;
    #1 reset = 0; En = 1; D = 2'b11;
    #1 reset = 0; En = 1; D = 2'b11;
    #1 reset = 0; En = 0; D = 2'b01;
    #1 reset = 0; En = 0; D = 2'b01;
    #1 reset = 0; En = 0; D = 2'b01;
    #1 reset = 0; En = 0; D = 2'b01;
    #1 reset = 0; En = 0; D = 2'b10;
  end

  initial
    #15 $finish;

  initial begin
    $dumpfile("FLIPFLOP2_tb.vcd");
    $dumpvars(0, testbench);
  end
endmodule //testbench

laboratorio 9/Ejercicio 1/FLIP-FLOP-D-2/FLIPFLOP2_tb.vcd
$date
	Sat Oct 31 03:41:32 2020
$end
$version
	Icarus Verilog
$end
$timescale
	1ps
$end
$scope module testbench $end
$var wire 2 ! Q [1:0] $end
$var reg 2 " D [1:0] $end
$var reg 1 # En $end
$var reg 1 $ clk $end
$var reg 1 % reset $end
$scope module b $end
$var wire 2 & D [1:0] $end
$var wire 1 # En $end
$var wire 1 $ clk $end
$var wire 1 % reset $end
$var wire 2 ' Q [1:0] $end
$scope module a $end
$var wire 1 ( D $end
$var wire 1 # En $end
$var wire 1 $ clk $end
$var wire 1 % reset $end
$var reg 1 ) Q $end
$upscope $end
$scope module a1 $end
$var wire 1 * D $end
$var wire 1 # En $end
$var wire 1 $ clk $end
$var wire 1 % reset $end
$var reg 1 + Q $end
$upscope $end
$upscope $end
$upscope $end
$enddefinitions $end
#0
$dumpvars
x+
x*
x)
x(
bx '
bx &
x%
x$
x#
bx "
bx !
$end
#1
0(
0*
b0 "
b0 &
0#
0%
0$
#2
0)
b0 !
b0 '
0+
1%
1$
#3
1*
b1 "
b1 &
1#
0%
0$
#4
b1 !
b1 '
1+
1(
0*
b10 "
b10 &
1$
#5
0$
#6
1)
b10 !
b10 '
0+
1$
#7
1*
b11 "
b11 &
0$
#8
b11 !
b11 '
1+
1$
#9
0$
#10
1$
#11
0(
b1 "
b1 &
0#
0$
#12
1$
#13
0$
#14
1$
#15
1(
0*
b10 "
b10 &
0$
