Laboratorio 5/Ejercicio4.v
//José Alejandro Duarte Godinez

// Se realiza el modulo del Mux 2:1
module Mux2(input wire S, D0, D1, output wire Y);
    //estabeciendo conexiones
  assign Y = S ? D1 : D0;

// Se finaliza el modulo
endmodule

// Se realiza el modulo del Mux 4:1
module Mux4(input wire S0, S1, D0, D1, D2, D3,  output wire Y1);
  // estableciendo conexines
  wire cbl1, cbl2;
  // Se intancia el Mux2:1
  Mux2 caja0(S0, D0, D1, cbl1);
  Mux2 caja1(S0, D2, D3, cbl2);
  Mux2 caja2(S1, cbl1, cbl2, Y1);

//Se finaliza el modulo
endmodule

// Se realiza el modulo del Mux 8:1
module Mux8(input wire D0, D1, D2, D3, D4, D5, D6, D7, S0, S1, S2, output wire Y2);
  // Estableciendo conectores
  wire cbl3, cbl4;
  // se instancian el Mux 4:1 y Mux 2:1
  Mux4 caja01(S0, S1, D0, D1, D2, D3, cbl3);
  Mux4 caja02(S0, S1, D4, D5, D6, D7, cbl4);
  Mux2 caja03(S2, cbl3, cbl4, Y2);

//Se finaliza el modulo
endmodule

// Se realiza el Mux 8:1 del ejercicio 1 de la tabla 1
module E1T1M8(input wire A, B, C, output Y4);

  wire V, G;
  assign V = 1;
  assign G = 0;
  //Se instancia el Mux 8:1
  Mux8 eje1t1(G, V, V, G, V, G, G, V, A, B, C, Y4);
  //Finaliza el modulo
endmodule

// Se realiza el Mux 4:1 del ejercicio 1 de la tabla 1
module E1T1M4(input wire A, B, C, output Y5);
  //se asignan variables
  wire NC;
  assign NC = ~C;

  //Se instancia el Mux 4:1
  Mux4 eje1t12( A, B, C, NC, NC, C, Y5);
endmodule

// Se realiza el Mux 2:1 del ejercicio 1 de la tabla 1
module E1T1M2(input wire A, B, C, output Y6);

  wire XOR,NXOR;
  assign XOR = B ^ C;
  assign NXOR = B ~^ C;

  Mux2 eje1t13(A, XOR, NXOR, Y6);

endmodule

module E1T2M8(input wire A, B, C, output Y7);

  wire V, G;
  assign V = 1;
  assign G = 0;
  //Se instancia el Mux 8:1
  Mux8 eje1t2(V, G, G, G, G, V, V, G, C, B, A, Y7);
  //Finaliza el modulo
endmodule

module E1T2M4(input wire A, B, C, output Y8);
  //se asignan variables
  wire NC;
  assign NC = ~C;
  assign G = 0;

  //Se instancia el Mux 4:1
  Mux4 eje1t22( B, A, NC, G, C, NC, Y8);
endmodule

module E1T2M2(input wire A, B, C, output Y9);
  wire XOR,NOR;
  assign NOR = B ~| C;
  assign XOR = B ^ C;

  Mux2 eje1t23(A, NOR, XOR, Y9);

endmodule

Laboratorio 5/Ejercicio4_tb.v
module testbench();

reg r1, r2, r3, r4, r5, r6, r7, r8, r9, r10, r11, r12,r13, r14, r15;
reg r16, r17, r18;
wire led0, led1, led2, led3, led4, led5;

E1T1M8 l1(r1, r2, r3, led0);
E1T1M4 l2(r4, r5, r6, led1);
E1T1M2 l3(r7, r8, r9, led2);
E1T2M8 l4(r10, r11, r12, led3);
E1T2M4 l5(r13, r14, r15, led4);
E1T2M2 l6(r16, r17, r18, led5);

initial begin //Mux 8:1 del ejercicio 1 de la tabla 1
  $display("\n\n");
  $display("A B C | Y");
  $display("------|---");
  $monitor("%b %b %b | %b", r1, r2, r3, led0);
      r1 = 0; r2 = 0; r3 = 0;
    #1r1 = 0; r2 = 0; r3 = 1;
    #1r1 = 0; r2 = 1; r3 = 0;
    #1r1 = 0; r2 = 1; r3 = 1;
    #1r1 = 1; r2 = 0; r3 = 0;
    #1r1 = 1; r2 = 0; r3 = 1;
    #1r1 = 1; r2 = 1; r3 = 0;
    #1r1 = 1; r2 = 1; r3 = 1;
end

initial begin//el Mux 4:1 del ejercicio 1 de la tabla 1
  #8
  $display("\n\n");
  $display("A B C | Y");
  $display("------|---");
  $monitor("%b %b %b | %b", r4, r5, r6, led1);
      r4 = 0; r5 = 0; r6 = 0;
    #1r4 = 0; r5 = 0; r6 = 1;
    #1r4 = 0; r5 = 1; r6 = 0;
    #1r4 = 0; r5 = 1; r6 = 1;
    #1r4 = 1; r5 = 0; r6 = 0;
    #1r4 = 1; r5 = 0; r6 = 1;
    #1r4 = 1; r5 = 1; r6 = 0;
    #1r4 = 1; r5 = 1; r6 = 1;

end

initial begin//el Mux 2:1 del ejercicio 1 de la tabla 1
  #16
  $display("\n\n");
  $display("A B C | Y");
  $display("------|---");
  $monitor("%b %b %b | %b", r7, r8, r9, led2);
      r7 = 0; r8 = 0; r9 = 0;
    #1r7 = 0; r8 = 0; r9 = 1;
    #1r7 = 0; r8 = 1; r9 = 0;
    #1r7 = 0; r8 = 1; r9 = 1;
    #1r7 = 1; r8 = 0; r9 = 0;
    #1r7 = 1; r8 = 0; r9 = 1;
    #1r7 = 1; r8 = 1; r9 = 0;
    #1r7 = 1; r8 = 1; r9 = 1;
end

initial begin//Mux 8:1 del ejercicio 1 de la tabla 2
  #24
  $display("\n\n");
  $display("A B C | Y");
  $display("------|---");
  $monitor("%b %b %b | %b", r10, r11, r12, led3);
      r10 = 0; r11 = 0; r12 = 0;
    #1r10 = 0; r11 = 0; r12 = 1;
    #1r10 = 0; r11 = 1; r12 = 0;
    #1r10 = 0; r11 = 1; r12 = 1;
    #1r10 = 1; r11 = 0; r12 = 0;
    #1r10 = 1; r11 = 0; r12 = 1;
    #1r10 = 1; r11 = 1; r12 = 0;
    #1r10 = 1; r11 = 1; r12 = 1;
end

initial begin////Mux 4:1 del ejercicio 1 de la tabla 2
  #32
  $display("\n\n");
  $display("A B C | Y");
  $display("------|---");
  $monitor("%b %b %b | %b", r13, r14, r15, led4);
      r13 = 0; r14 = 0; r15 = 0;
    #1r13 = 0; r14 = 0; r15 = 1;
    #1r13 = 0; r14 = 1; r15 = 0;
    #1r13 = 0; r14 = 1; r15 = 1;
    #1r13 = 1; r14 = 0; r15 = 0;
    #1r13 = 1; r14 = 0; r15 = 1;
    #1r13 = 1; r14 = 1; r15 = 0;
    #1r13 = 1; r14 = 1; r15 = 1;
end
initial begin//Mux 2:1 del ejercicio 1 de la tabla 2
  #40
  $display("\n\n");
  $display("A B C | Y");
  $display("------|---");
  $monitor("%b %b %b | %b", r16, r17, r18, led5);
      r16 = 0; r17 = 0; r18 = 0;
    #1r16 = 0; r17 = 0; r18 = 1;
    #1r16 = 0; r17 = 1; r18 = 0;
    #1r16 = 0; r17 = 1; r18 = 1;
    #1r16 = 1; r17 = 0; r18 = 0;
    #1r16 = 1; r17 = 0; r18 = 1;
    #1r16 = 1; r17 = 1; r18 = 0;
    #1r16 = 1; r17 = 1; r18 = 1;
end

initial begin
    $dumpfile("Ejercicio4_tb.vcd");
    $dumpvars(0, testbench);
  end

initial
    #48$finish;




endmodule

Laboratorio 5/Ejercicio4_tb.vcd
$date
	Sun Aug 16 00:54:33 2020
$end
$version
	Icarus Verilog
$end
$timescale
	1ps
$end
$scope module testbench $end
$var wire 1 ! led5 $end
$var wire 1 " led4 $end
$var wire 1 # led3 $end
$var wire 1 $ led2 $end
$var wire 1 % led1 $end
$var wire 1 & led0 $end
$var reg 1 ' r1 $end
$var reg 1 ( r10 $end
$var reg 1 ) r11 $end
$var reg 1 * r12 $end
$var reg 1 + r13 $end
$var reg 1 , r14 $end
$var reg 1 - r15 $end
$var reg 1 . r16 $end
$var reg 1 / r17 $end
$var reg 1 0 r18 $end
$var reg 1 1 r2 $end
$var reg 1 2 r3 $end
$var reg 1 3 r4 $end
$var reg 1 4 r5 $end
$var reg 1 5 r6 $end
$var reg 1 6 r7 $end
$var reg 1 7 r8 $end
$var reg 1 8 r9 $end
$scope module l1 $end
$var wire 1 ' A $end
$var wire 1 1 B $end
$var wire 1 2 C $end
$var wire 1 9 G $end
$var wire 1 : V $end
$var wire 1 & Y4 $end
$scope module eje1t1 $end
$var wire 1 9 D0 $end
$var wire 1 : D1 $end
$var wire 1 : D2 $end
$var wire 1 9 D3 $end
$var wire 1 : D4 $end
$var wire 1 9 D5 $end
$var wire 1 9 D6 $end
$var wire 1 : D7 $end
$var wire 1 ' S0 $end
$var wire 1 1 S1 $end
$var wire 1 2 S2 $end
$var wire 1 ; cbl4 $end
$var wire 1 < cbl3 $end
$var wire 1 & Y2 $end
$scope module caja01 $end
$var wire 1 9 D0 $end
$var wire 1 : D1 $end
$var wire 1 : D2 $end
$var wire 1 9 D3 $end
$var wire 1 ' S0 $end
$var wire 1 1 S1 $end
$var wire 1 = cbl2 $end
$var wire 1 > cbl1 $end
$var wire 1 < Y1 $end
$scope module caja0 $end
$var wire 1 9 D0 $end
$var wire 1 : D1 $end
$var wire 1 ' S $end
$var wire 1 > Y $end
$upscope $end
$scope module caja1 $end
$var wire 1 : D0 $end
$var wire 1 9 D1 $end
$var wire 1 ' S $end
$var wire 1 = Y $end
$upscope $end
$scope module caja2 $end
$var wire 1 > D0 $end
$var wire 1 = D1 $end
$var wire 1 1 S $end
$var wire 1 < Y $end
$upscope $end
$upscope $end
$scope module caja02 $end
$var wire 1 : D0 $end
$var wire 1 9 D1 $end
$var wire 1 9 D2 $end
$var wire 1 : D3 $end
$var wire 1 ' S0 $end
$var wire 1 1 S1 $end
$var wire 1 ? cbl2 $end
$var wire 1 @ cbl1 $end
$var wire 1 ; Y1 $end
$scope module caja0 $end
$var wire 1 : D0 $end
$var wire 1 9 D1 $end
$var wire 1 ' S $end
$var wire 1 @ Y $end
$upscope $end
$scope module caja1 $end
$var wire 1 9 D0 $end
$var wire 1 : D1 $end
$var wire 1 ' S $end
$var wire 1 ? Y $end
$upscope $end
$scope module caja2 $end
$var wire 1 @ D0 $end
$var wire 1 ? D1 $end
$var wire 1 1 S $end
$var wire 1 ; Y $end
$upscope $end
$upscope $end
$scope module caja03 $end
$var wire 1 < D0 $end
$var wire 1 ; D1 $end
$var wire 1 2 S $end
$var wire 1 & Y $end
$upscope $end
$upscope $end
$upscope $end
$scope module l2 $end
$var wire 1 3 A $end
$var wire 1 4 B $end
$var wire 1 5 C $end
$var wire 1 A NC $end
$var wire 1 % Y5 $end
$scope module eje1t12 $end
$var wire 1 5 D0 $end
$var wire 1 A D1 $end
$var wire 1 A D2 $end
$var wire 1 5 D3 $end
$var wire 1 3 S0 $end
$var wire 1 4 S1 $end
$var wire 1 B cbl2 $end
$var wire 1 C cbl1 $end
$var wire 1 % Y1 $end
$scope module caja0 $end
$var wire 1 5 D0 $end
$var wire 1 A D1 $end
$var wire 1 3 S $end
$var wire 1 C Y $end
$upscope $end
$scope module caja1 $end
$var wire 1 A D0 $end
$var wire 1 5 D1 $end
$var wire 1 3 S $end
$var wire 1 B Y $end
$upscope $end
$scope module caja2 $end
$var wire 1 C D0 $end
$var wire 1 B D1 $end
$var wire 1 4 S $end
$var wire 1 % Y $end
$upscope $end
$upscope $end
$upscope $end
$scope module l3 $end
$var wire 1 6 A $end
$var wire 1 7 B $end
$var wire 1 8 C $end
$var wire 1 D NXOR $end
$var wire 1 E XOR $end
$var wire 1 $ Y6 $end
$scope module eje1t13 $end
$var wire 1 E D0 $end
$var wire 1 D D1 $end
$var wire 1 6 S $end
$var wire 1 $ Y $end
$upscope $end
$upscope $end
$scope module l4 $end
$var wire 1 ( A $end
$var wire 1 ) B $end
$var wire 1 * C $end
$var wire 1 F G $end
$var wire 1 G V $end
$var wire 1 # Y7 $end
$scope module eje1t2 $end
$var wire 1 G D0 $end
$var wire 1 F D1 $end
$var wire 1 F D2 $end
$var wire 1 F D3 $end
$var wire 1 F D4 $end
$var wire 1 G D5 $end
$var wire 1 G D6 $end
$var wire 1 F D7 $end
$var wire 1 * S0 $end
$var wire 1 ) S1 $end
$var wire 1 ( S2 $end
$var wire 1 H cbl4 $end
$var wire 1 I cbl3 $end
$var wire 1 # Y2 $end
$scope module caja01 $end
$var wire 1 G D0 $end
$var wire 1 F D1 $end
$var wire 1 F D2 $end
$var wire 1 F D3 $end
$var wire 1 * S0 $end
$var wire 1 ) S1 $end
$var wire 1 J cbl2 $end
$var wire 1 K cbl1 $end
$var wire 1 I Y1 $end
$scope module caja0 $end
$var wire 1 G D0 $end
$var wire 1 F D1 $end
$var wire 1 * S $end
$var wire 1 K Y $end
$upscope $end
$scope module caja1 $end
$var wire 1 F D0 $end
$var wire 1 F D1 $end
$var wire 1 * S $end
$var wire 1 J Y $end
$upscope $end
$scope module caja2 $end
$var wire 1 K D0 $end
$var wire 1 J D1 $end
$var wire 1 ) S $end
$var wire 1 I Y $end
$upscope $end
$upscope $end
$scope module caja02 $end
$var wire 1 F D0 $end
$var wire 1 G D1 $end
$var wire 1 G D2 $end
$var wire 1 F D3 $end
$var wire 1 * S0 $end
$var wire 1 ) S1 $end
$var wire 1 L cbl2 $end
$var wire 1 M cbl1 $end
$var wire 1 H Y1 $end
$scope module caja0 $end
$var wire 1 F D0 $end
$var wire 1 G D1 $end
$var wire 1 * S $end
$var wire 1 M Y $end
$upscope $end
$scope module caja1 $end
$var wire 1 G D0 $end
$var wire 1 F D1 $end
$var wire 1 * S $end
$var wire 1 L Y $end
$upscope $end
$scope module caja2 $end
$var wire 1 M D0 $end
$var wire 1 L D1 $end
$var wire 1 ) S $end
$var wire 1 H Y $end
$upscope $end
$upscope $end
$scope module caja03 $end
$var wire 1 I D0 $end
$var wire 1 H D1 $end
$var wire 1 ( S $end
$var wire 1 # Y $end
$upscope $end
$upscope $end
$upscope $end
$scope module l5 $end
$var wire 1 + A $end
$var wire 1 , B $end
$var wire 1 - C $end
$var wire 1 N G $end
$var wire 1 O NC $end
$var wire 1 " Y8 $end
$scope module eje1t22 $end
$var wire 1 O D0 $end
$var wire 1 N D1 $end
$var wire 1 - D2 $end
$var wire 1 O D3 $end
$var wire 1 , S0 $end
$var wire 1 + S1 $end
$var wire 1 P cbl2 $end
$var wire 1 Q cbl1 $end
$var wire 1 " Y1 $end
$scope module caja0 $end
$var wire 1 O D0 $end
$var wire 1 N D1 $end
$var wire 1 , S $end
$var wire 1 Q Y $end
$upscope $end
$scope module caja1 $end
$var wire 1 - D0 $end
$var wire 1 O D1 $end
$var wire 1 , S $end
$var wire 1 P Y $end
$upscope $end
$scope module caja2 $end
$var wire 1 Q D0 $end
$var wire 1 P D1 $end
$var wire 1 + S $end
$var wire 1 " Y $end
$upscope $end
$upscope $end
$upscope $end
$scope module l6 $end
$var wire 1 . A $end
$var wire 1 / B $end
$var wire 1 0 C $end
$var wire 1 R NOR $end
$var wire 1 S XOR $end
$var wire 1 ! Y9 $end
$scope module eje1t23 $end
$var wire 1 R D0 $end
$var wire 1 S D1 $end
$var wire 1 . S $end
$var wire 1 ! Y $end
$upscope $end
$upscope $end
$upscope $end
$enddefinitions $end
#0
$dumpvars
xS
xR
xQ
xP
xO
0N
xM
xL
xK
0J
xI
xH
1G
0F
xE
xD
xC
xB
xA
1@
0?
0>
1=
0<
1;
1:
09
x8
x7
x6
x5
x4
x3
02
01
x0
x/
x.
x-
x,
x+
x*
x)
x(
0'
0&
x%
x$
x#
x"
x!
$end
#1
1&
12
#2
1<
0;
02
11
#3
0&
12
#4
1&
1>
0=
0@
1?
02
01
1'
#5
0&
12
#6
0<
1;
02
11
#7
1&
12
#8
1B
1A
0%
0C
05
04
03
#9
0B
1%
0A
1C
15
#10
1B
1A
0C
1%
05
14
#11
0%
0B
0A
1C
15
#12
1%
1A
1C
05
04
13
#13
0%
0C
0A
1B
15
#14
1C
1A
0B
0%
05
14
#15
0C
1%
0A
1B
15
#16
0$
0E
1D
08
07
06
#17
1$
1E
0D
18
#18
08
17
#19
0$
0E
1D
18
#20
1$
08
07
16
#21
0$
1E
0D
18
#22
08
17
#23
1$
0E
1D
18
#24
1#
1I
0H
1K
0M
1L
0*
0)
0(
#25
0#
0I
1H
0K
1M
0L
1*
#26
1K
0M
1L
1H
0*
1)
#27
0H
0K
1M
0L
1*
#28
1I
0#
1K
0M
1L
0H
0*
0)
1(
#29
1#
0I
1H
0K
1M
0L
1*
#30
1#
1K
0M
1L
1H
0*
1)
#31
0#
0H
0K
1M
0L
1*
#32
1"
1Q
1O
0P
0-
0,
0+
#33
0"
0Q
0O
1P
1-
#34
1O
1P
0-
1,
#35
0P
0O
1-
#36
1Q
1O
0-
0,
1+
#37
0Q
1"
0O
1P
1-
#38
1"
1O
1P
0-
1,
#39
0"
0P
0O
1-
#40
1!
1R
0S
00
0/
0.
#41
0!
0R
1S
10
#42
00
1/
#43
0S
10
#44
1R
00
0/
1.
#45
1!
0R
1S
10
#46
00
1/
#47
0!
0S
10
