Laboratorio 3/03-TABLA-SOP/TABLA3_SOP.v
module TABLA3_SOP();


reg A, B, C, D;
wire a0, a1, a2, a3, b1, b2, b3, b4, b5, b6, b7, out;

not ja0(a0, D);
not ja1(a1, A);
not ja2(a2, B);
not ja3(a3, C);
and ja4(b1, a1, a2, a3, a0);
and ja5(b2, a1, a2, a3, D);
and ja6(b3, a1, a2, C, a0);
and ja7(b4, a1, a2, C, D);
and ja8(b5, A, a2, a3, a0);
and ja9(b6, A, a2, C, a0);
and ja10(b7, A, B, C, a0);
or ja13(out, b1, b2, b3, b4, b5, b6, b7);

initial begin
  $display("A B C D | Y");
  $monitor("%b %b %b %b | %b", A, B, C, D, out);
  A = 0; B = 0; C = 0; D = 0;
  #1 D=1;
  #1 C=1; D=0;
  #1 D=1;
  #1 B=1; C=0; D=0;
  #1 D=1;
  #1 C=1; D=0;
  #1 D=1;
  #1 A=1; B=0; C=0; D=0;
  #1 D=1;
  #1 C=1; D=0;
  #1 D=1;
  #1 B=1; C=0; D=0;
  #1 D=1;
  #1 C=1; D=0;
  #1 D=1;
  #1 $finish;
end

initial
    begin
      $dumpfile("TABLA3_SOP_tb.vcd");
      $dumpvars(0, TABLA3_SOP);
    end
endmodule

//Se utiliza apio sim

Laboratorio 3/03-TABLA-SOP/TABLA3_SOP_tb.vcd
$date
	Sat Aug 01 15:57:18 2020
$end
$version
	Icarus Verilog
$end
$timescale
	1ps
$end
$scope module TABLA3_SOP $end
$var wire 1 ! a0 $end
$var wire 1 " a1 $end
$var wire 1 # a2 $end
$var wire 1 $ a3 $end
$var wire 1 % b1 $end
$var wire 1 & b2 $end
$var wire 1 ' b3 $end
$var wire 1 ( b4 $end
$var wire 1 ) b5 $end
$var wire 1 * b6 $end
$var wire 1 + b7 $end
$var wire 1 , out $end
$var reg 1 - A $end
$var reg 1 . B $end
$var reg 1 / C $end
$var reg 1 0 D $end
$upscope $end
$enddefinitions $end
#0
$dumpvars
00
0/
0.
0-
1,
0+
0*
0)
0(
0'
0&
1%
1$
1#
1"
1!
$end
#1
0%
1&
0!
10
#2
1'
0&
1!
0$
00
1/
#3
0'
1(
0!
10
#4
0,
1!
0(
1$
0#
00
0/
1.
#5
0!
10
#6
1!
0$
00
1/
#7
0!
10
#8
1,
1)
1!
1$
1#
0"
00
0/
0.
1-
#9
0,
0)
0!
10
#10
1,
1*
1!
0$
00
1/
#11
0,
0*
0!
10
#12
1!
1$
0#
00
0/
1.
#13
0!
10
#14
1,
1+
1!
0$
00
1/
#15
0,
0+
0!
10
