laboratorio 10/Ejercicio 2/bloque2.v
module BUSDRIVER1(input [3:0] Entrada, input En, output [3:0] salida);
  assign salida = (En) ? Entrada:4'bz;
endmodule



module BUSDRIVER2(input [3:0] Entrada, input En, output [3:0] salida);
  assign salida = (En) ? Entrada:4'bz;
endmodule



module ALU (
  input wire [3:0] A,B,
  input wire [2:0]commando,
  output reg [3:0]Out,
  output reg carry,
  output reg zero);

  reg[4:0]w;
  always @ (A or B or commando) begin


    case(commando)
      3'b000: begin
                w = 5'b00000;
                w = A;
                carry = 1'b0;
                zero = (w == 5'b00000) ? 1:0;
                Out = w[3:0];
              end

      3'b010: begin
                w = 5'b00000;
                w = B;
                carry = 1'b0;
                zero = (w == 5'b00000) ? 1:0;
                Out = w[3:0];
              end

      3'b011: begin //SUMA
                w = 5'b00000;
                w = A + B;
                carry = (w[4] == 1) ? 1:0;
                zero = (w == 5'b00000) ? 1:0;
                Out = w[3:0];
              end

      3'b001: begin
                  w = 5'b00000;
                  w = A - B;
                  carry = (w[4] == 1) ? 1:0;
                  zero = (w == 5'b00000) ? 1:0;
                  Out = w[3:0];
                end

      3'b100:begin
                w = 5'b00000;
                w = ~(A & B);
                carry = 1'b0;
                zero = (w == 5'b00000) ? 1:0;
                Out = w[3:0];
              end
    endcase
  end
endmodule //ALU

module acumulador(input clk, reset,En, input [3:0]D, output reg [3:0]Q);
  always @ (posedge clk or posedge reset)begin
    if (reset)
      Q <= 4'b0;
    else if (En)
      Q <= D;
  end
endmodule



module ejercicio2(input clk, reset, EN_BUS1, EN_BUS2, EN_ACU,
  input [2:0]selct, input [3:0]D, output carry, zero, output [3:0]salida);

  wire [3:0]data_bus;
  wire [3:0]respuesta_ALU;
  wire [3:0]accu;

  BUSDRIVER1 c1(D, EN_BUS1, data_bus);
  ALU c2(accu, data_bus, selct, respuesta_ALU, carry, zero);
  acumulador c3(clk, reset, EN_ACU, respuesta_ALU, accu);
  BUSDRIVER2 c4(respuesta_ALU, EN_BUS2, salida);

endmodule

laboratorio 10/Ejercicio 2/bloque2_tb.v
module testbench();

reg clk, reset, EN_BUS1, EN_BUS2, EN_ACU;
reg [2:0]selct;
reg [3:0]D;
wire carry, zero;
wire [3:0]salida;

ejercicio2 a2(clk, reset, EN_BUS1, EN_BUS2, EN_ACU, selct,
  D, carry, zero, salida);

  always
    begin
    #1 clk = ~clk;
  end

  initial begin
  #1
  $display("--------------------------------------------------|--------------------|");
  $display(" clk reset EN_BUS1 EN_BUS2 EN_ACU    D   SELECTOR  |  ZERO CARRY SALIDA |");
  $display("--------------------------------------------------|--------------------|");
  $monitor("%b    %b       %b       %b       %b    %b    %b     |    %b    %b    %b  |", clk, reset, EN_BUS1, EN_BUS2, EN_ACU, D, selct, zero, carry, salida);
     clk = 0; reset = 0; EN_BUS1 = 0; EN_BUS2 = 0; EN_ACU = 0; D = 4'b0000; selct = 3'b000;
  #1 reset = 1; EN_BUS1 = 0; EN_BUS2 = 0; EN_ACU = 0;
  #1 reset = 0; EN_BUS1 = 1; EN_BUS2 = 1; EN_ACU = 1; selct = 3'b010; D = 4'b1000;
  #1 reset = 0; EN_BUS1 = 1; EN_BUS2 = 1; EN_ACU = 1; selct = 3'b010; D = 4'b1000;
  #1 reset = 0; EN_BUS1 = 1; EN_BUS2 = 1; EN_ACU = 1; selct = 3'b010; D = 4'b1000;
  #1 reset = 0; EN_BUS1 = 1; EN_BUS2 = 1; EN_ACU = 1; selct = 3'b011; D = 4'b1000;
  #1 reset = 0; EN_BUS1 = 1; EN_BUS2 = 1; EN_ACU = 1; selct = 3'b011; D = 4'b1000;
  #1 reset = 0; EN_BUS1 = 1; EN_BUS2 = 1; EN_ACU = 1; selct = 3'b010; D = 4'b0001;
  #1 reset = 0; EN_BUS1 = 1; EN_BUS2 = 1; EN_ACU = 1; selct = 3'b010; D = 4'b0001;
  #1 reset = 0; EN_BUS1 = 1; EN_BUS2 = 1; EN_ACU = 1; selct = 3'b001; D = 4'b0001;
  end

  initial
   #10 $finish;


  initial begin
    $dumpfile("bloque2_tb.vcd");
    $dumpvars(0, testbench);
  end
endmodule //

laboratorio 10/Ejercicio 2/bloque2_tb.vcd
$date
	Sat Nov 07 20:31:44 2020
$end
$version
	Icarus Verilog
$end
$timescale
	1ps
$end
$scope module testbench $end
$var wire 1 ! zero $end
$var wire 4 " salida [3:0] $end
$var wire 1 # carry $end
$var reg 4 $ D [3:0] $end
$var reg 1 % EN_ACU $end
$var reg 1 & EN_BUS1 $end
$var reg 1 ' EN_BUS2 $end
$var reg 1 ( clk $end
$var reg 1 ) reset $end
$var reg 3 * selct [2:0] $end
$scope module a2 $end
$var wire 4 + D [3:0] $end
$var wire 1 % EN_ACU $end
$var wire 1 & EN_BUS1 $end
$var wire 1 ' EN_BUS2 $end
$var wire 1 ( clk $end
$var wire 1 ) reset $end
$var wire 3 , selct [2:0] $end
$var wire 1 ! zero $end
$var wire 4 - salida [3:0] $end
$var wire 4 . respuesta_ALU [3:0] $end
$var wire 4 / data_bus [3:0] $end
$var wire 1 # carry $end
$var wire 4 0 accu [3:0] $end
$scope module c1 $end
$var wire 1 & En $end
$var wire 4 1 Entrada [3:0] $end
$var wire 4 2 salida [3:0] $end
$upscope $end
$scope module c2 $end
$var wire 4 3 B [3:0] $end
$var wire 3 4 commando [2:0] $end
$var wire 4 5 A [3:0] $end
$var reg 4 6 Out [3:0] $end
$var reg 1 # carry $end
$var reg 5 7 w [4:0] $end
$var reg 1 ! zero $end
$upscope $end
$scope module c3 $end
$var wire 4 8 D [3:0] $end
$var wire 1 % En $end
$var wire 1 ( clk $end
$var wire 1 ) reset $end
$var reg 4 9 Q [3:0] $end
$upscope $end
$scope module c4 $end
$var wire 1 ' En $end
$var wire 4 : Entrada [3:0] $end
$var wire 4 ; salida [3:0] $end
$upscope $end
$upscope $end
$upscope $end
$enddefinitions $end
#0
$dumpvars
bx ;
bx :
bx 9
bx 8
bx 7
bx 6
bx 5
bx 4
bx 3
bx 2
bx 1
bx 0
bx /
bx .
bx -
bx ,
bx +
bx *
x)
x(
x'
x&
x%
bx $
x#
bx "
x!
$end
#1
0#
b0xxxx 7
bz "
bz -
bz ;
bz /
bz 2
bz 3
b0 *
b0 ,
b0 4
b0 $
b0 +
b0 1
0%
0'
0&
0)
0(
#2
b0 .
b0 6
b0 8
b0 :
1!
b0 7
b0 0
b0 5
b0 9
1)
1(
#3
b1000 .
b1000 6
b1000 8
b1000 :
0!
b1000 7
b1000 "
b1000 -
b1000 ;
b1000 /
b1000 2
b1000 3
b1000 $
b1000 +
b1000 1
b10 *
b10 ,
b10 4
1%
1'
1&
0)
0(
#4
b1000 7
b1000 0
b1000 5
b1000 9
1(
#5
0(
#6
b0 "
b0 -
b0 ;
b0 .
b0 6
b0 8
b0 :
1#
b10000 7
b11 *
b11 ,
b11 4
1(
#7
0(
#8
b0 0
b0 5
b0 9
b1 "
b1 -
b1 ;
b1 /
b1 2
b1 3
b1 .
b1 6
b1 8
b1 :
0#
b1 7
b1 $
b1 +
b1 1
b10 *
b10 ,
b10 4
1(
#9
0(
#10
1!
b1 0
b1 5
b1 9
b0 "
b0 -
b0 ;
b0 .
b0 6
b0 8
b0 :
0#
b0 7
b1 *
b1 ,
b1 4
1(
