Laboratorio 8/ALU/Alejandro-Duarte-19446-21-ALU.v
module ALU(
  input wire [3:0]variable1,
  input wire [3:0]variable2,
  input wire [2:0]comando,
  output reg [3:0]respuesta
  );
  always @ (variable1,variable2,comando) begin
    case(comando)
        3'b000: respuesta = variable1 & variable2;
        3'b001: respuesta = variable1 | variable2;
        3'b010: respuesta = variable1 + variable2;
        3'b011: respuesta = 4'b0000;
        3'b100: respuesta = variable1 & ~variable2;
        3'b101: respuesta = variable1 | ~variable2;
        3'b110: respuesta = variable1 - variable2;
        3'b111: respuesta = (variable1 < variable2) ? 1:0;
        default: respuesta = 4'b0000;
    endcase
  end
endmodule

Laboratorio 8/ALU/Alejandro-Duarte-19446-21-ALU_tb.v
module testbench();

reg [3:0]variable1;
reg [3:0]variable2;
reg [2:0]comando;
wire [3:0]respuesta;

ALU c(variable1,variable2,comando,respuesta);

initial begin
  #1
  $display("|---------|-----------|------------|-----------|");
  $display("| Comando | Variable1 | Varaiable2 | Respuesta |");
  $display("|---------|-----------|------------|-----------|");
  $monitor("|   %b   |   %b    |     %b   |    %b   |", comando,variable1,variable2,respuesta);
       comando = 3'b000; variable1 = 4'b0010; variable2 = 4'b1100;
    #1 comando = 3'b001; variable1 = 4'b0011; variable2 = 4'b1010;
    #1 comando = 3'b010; variable1 = 4'b0110; variable2 = 4'b0000;
    #1 comando = 3'b011; variable1 = 4'b0101; variable2 = 4'b1000;
    #1 comando = 3'b100; variable1 = 4'b0001; variable2 = 4'b0110;
    #1 comando = 3'b101; variable1 = 4'b1110; variable2 = 4'b0111;
    #1 comando = 3'b110; variable1 = 4'b1111; variable2 = 4'b1100;
    #1 comando = 3'b111; variable1 = 4'b0001; variable2 = 4'b0000;

end
initial
  #10 $finish;

initial begin
  $dumpfile("Alejandro-Duarte-19446-21-ALU_tb.vcd");
  $dumpvars(0, testbench);
end


endmodule

Laboratorio 8/ALU/Alejandro-Duarte-19446-21-ALU_tb.vcd
$date
	Sat Oct 24 18:36:17 2020
$end
$version
	Icarus Verilog
$end
$timescale
	1ps
$end
$scope module testbench $end
$var wire 4 ! respuesta [3:0] $end
$var reg 3 " comando [2:0] $end
$var reg 4 # variable1 [3:0] $end
$var reg 4 $ variable2 [3:0] $end
$scope module c $end
$var wire 3 % comando [2:0] $end
$var wire 4 & variable1 [3:0] $end
$var wire 4 ' variable2 [3:0] $end
$var reg 4 ( respuesta [3:0] $end
$upscope $end
$upscope $end
$enddefinitions $end
#0
$dumpvars
bx (
bx '
bx &
bx %
bx $
bx #
bx "
bx !
$end
#1
b0 !
b0 (
b1100 $
b1100 '
b10 #
b10 &
b0 "
b0 %
#2
b1011 !
b1011 (
b1010 $
b1010 '
b11 #
b11 &
b1 "
b1 %
#3
b110 !
b110 (
b0 $
b0 '
b110 #
b110 &
b10 "
b10 %
#4
b0 !
b0 (
b1000 $
b1000 '
b101 #
b101 &
b11 "
b11 %
#5
b1 !
b1 (
b110 $
b110 '
b1 #
b1 &
b100 "
b100 %
#6
b1110 !
b1110 (
b111 $
b111 '
b1110 #
b1110 &
b101 "
b101 %
#7
b11 !
b11 (
b1100 $
b1100 '
b1111 #
b1111 &
b110 "
b110 %
#8
b0 !
b0 (
b0 $
b0 '
b1 #
b1 &
b111 "
b111 %
