Laboratorio 3/03-TABLA-POS/TABLA3_POS.v
module TABLA3_POS();


reg A, B, C, D;
wire a0,a1, a2, a3, b1, b2, b3, b4, b5, b6, b7, b8, b9, out;

not ja0(a0, D);
not ja1(a1, A);
not ja2(a2, B);
not ja3(a3, C);
or ja4(b1, A, a2, C, D);
or ja5(b2, A, a2, C, a0);
or ja6(b3, A, a2, a3, D);
or ja7(b4, A, a2, a3, a0);
or ja8(b5, a1, B, C, a0);
or ja9(b6, a1, B, a3, a0);
or ja10(b7, a1, a2, C, D);
or ja11(b8, a1, a2, C, a0);
or ja12(b9, a1, a2, a3, a0);
and ja13(out, b1, b2, b3, b4, b5, b6, b7, b8, b9);

initial begin
  $display("A B C D | Y");
  $monitor("%b %b %b %b | %b", A, B, C, D, out);
  A = 0; B = 0; C = 0; D = 0;
  #1 D=1;
  #1 C=1; D=0;
  #1 D=1;
  #1 B=1; C=0; D=0;
  #1 D=1;
  #1 C=1; D=0;
  #1 D=1;
  #1 A=1; B=0; C=0; D=0;
  #1 D=1;
  #1 C=1; D=0;
  #1 D=1;
  #1 B=1; C=0; D=0;
  #1 D=1;
  #1 C=1; D=0;
  #1 D=1;
  #1 $finish;
end

initial
    begin
      $dumpfile("TABLA3_POS_tb.vcd");
      $dumpvars(0, TABLA3_POS);
    end
endmodule

//Se utilza apio sim

Laboratorio 3/03-TABLA-POS/TABLA3_POS_tb.vcd
$date
	Sat Aug 01 15:54:45 2020
$end
$version
	Icarus Verilog
$end
$timescale
	1ps
$end
$scope module TABLA3_POS $end
$var wire 1 ! a0 $end
$var wire 1 " a1 $end
$var wire 1 # a2 $end
$var wire 1 $ a3 $end
$var wire 1 % b1 $end
$var wire 1 & b2 $end
$var wire 1 ' b3 $end
$var wire 1 ( b4 $end
$var wire 1 ) b5 $end
$var wire 1 * b6 $end
$var wire 1 + b7 $end
$var wire 1 , b8 $end
$var wire 1 - b9 $end
$var wire 1 . out $end
$var reg 1 / A $end
$var reg 1 0 B $end
$var reg 1 1 C $end
$var reg 1 2 D $end
$upscope $end
$enddefinitions $end
#0
$dumpvars
02
01
00
0/
1.
1-
1,
1+
1*
1)
1(
1'
1&
1%
1$
1#
1"
1!
$end
#1
0!
12
#2
1!
0$
02
11
#3
0!
12
#4
0.
1!
1&
0%
1$
0#
02
01
10
#5
0&
1%
0!
12
#6
0'
1!
1&
0$
02
11
#7
0(
1'
0!
12
#8
1.
1!
1$
1*
1)
1#
1(
0"
02
01
00
1/
#9
0.
0)
0!
12
#10
1.
1!
1)
0$
02
11
#11
0.
0*
0!
12
#12
1!
1,
0+
1$
1*
0#
02
01
10
#13
0,
1+
0!
12
#14
1.
1!
1,
0$
02
11
#15
0.
0-
0!
12
