Laboratorio 4/ejercicio 4/Gate_level_y_operadores.v
//Se realizo la ecuacion reducida de la tabla 02 del ejercicio 1
module gatelevel(input wire A, B, C, output wire out);

  not (out, B);

endmodule

//Se realiza la ecuacion reducida de la tabla 03 del ejercicio 1
module gatelevel2(input wire A, B, C, D, output out);

  wire a1, a2, a3, a4, b1, b2, b3, b4, b5, b6, b7, b8;

  not (a1, A);
  not (a2, B);
  not (a3, C);
  not (a4, D);
  and (b1, a1, a2, a3, a4);
  and (b2, a1, a2, C, D);
  and (b3, a1, B, a3, D);
  and (b4, a1, B, C, a4);
  and (b5, A, B, a3, a4);
  and (b6, A, B, C, D);
  and (b7, A, a2, a3, D);
  and (b8, A, a2, C, a4);
  or (out, b1, b2, b3, b4, b5, b6, b7, b8);

endmodule

// Se realizo la ecuacion reducida de la ecuacion 1 del ejercicio 2
module gatelevel3(input wire A, B, C, D, output out);

  wire c1, c2, c3, c4, d1, d2, d3, d4;

  not (c1, A);
  not (c2, B);
  not (c3, C);
  not (c4, D);
  and (d1, A, c3);
  and (d2, A, c4);
  and (d3, A, c2);
  and (d4, c2, c3, c4);
  or (out, d1, d2, d3, d4);

endmodule

// Se realizo la ecuacion reducida de la ecuacion 2 del ejercicio 2
module gatelevel4(input wire A, B, C, output out);

  wire e1;

  not (e1, B);
  or (out, e1, C);

endmodule

// Se realizo la ecuacion reducida de la tabla 01 del ejercicio 1
module operador1(input wire A, B, C, output wire out);

  assign out = (A & C) | (~A & ~C) | (~B & ~C);

endmodule

// Se realizo la ecuacion reducida de la tabla 04 del ejercicio 1
module operador2(input wire A, B, C, D, output wire out);

  assign out = (B & D) | (A & ~D) | (A & C);

endmodule

// Se realizo la ecuacion reducida de la ecuacion 3 del ejercicio 2
module operador3(input wire A, B, C, D, output wire out);

  assign out = (B) | (~C & D) | (A & D);

endmodule

// Se realizo la ecuacion reducida de la ecuacion 4 del ejercicio 2
module operador4(input wire A, B, C, output wire out);

  assign out = (B) | (~A & ~C);

endmodule

Laboratorio 4/ejercicio 4/Gate_level_y_operadores_tb.v
module testbench();
  reg ja1, ja2, ja3, ja4, ja5, ja6, ja7, ja8, ja9, ja10, ja11, ja12, ja13, ja14;
  reg ja15, ja16, ja17, ja18, ja19, ja20, ja21, jo1, jo2, jo3, jo4, jo5, jo6, jo7;
  wire led, led1, led2, led3, led4, led5, led6, led7;

  gatelevel G(ja1, ja2, ja3, led);
  gatelevel2 G1(ja4, ja5, ja6, ja7, led1);
  gatelevel3 G2(ja8, ja9, ja10, ja11, led2);
  gatelevel4 G3(ja12, ja13, ja14, led3);
  operador1 OP1(ja15, ja16, ja17, led4);
  operador2 OP2(ja18, ja19, ja20, ja21, led5);
  operador3 OP3(jo1, jo2, jo3, jo4, led6);
  operador4 OP4(jo5, jo6, jo7, led7);

  initial begin //gatelevel
    $display("\n\n");
    $display("A B C | Y");
    $display("------|---");
    $monitor("%b %b %b | %b", ja1, ja2, ja3, led);
      ja1 = 0; ja2 = 0; ja3 = 0;
    #1ja1 = 0; ja2 = 0; ja3 = 1;
    #1ja1 = 0; ja2 = 1; ja3 = 0;
    #1ja1 = 0; ja2 = 1; ja3 = 1;
    #1ja1 = 1; ja2 = 0; ja3 = 0;
    #1ja1 = 1; ja2 = 0; ja3 = 1;
    #1ja1 = 1; ja2 = 1; ja3 = 0;
    #1ja1 = 1; ja2 = 1; ja3 = 1;
  end

  initial begin //gatelevel2
    #8
    $display("\n\n");
    $display("A B C D | Y");
    $display("--------|---");
    $monitor("%b %b %b %b | %b", ja4, ja5, ja6, ja7, led1);
      ja4 = 0; ja5 = 0; ja6 = 0; ja7 = 0;
    #1ja4 = 0; ja5 = 0; ja6 = 0; ja7 = 1;
    #1ja4 = 0; ja5 = 0; ja6 = 1; ja7 = 0;
    #1ja4 = 0; ja5 = 0; ja6 = 1; ja7 = 1;
    #1ja4 = 0; ja5 = 1; ja6 = 0; ja7 = 0;
    #1ja4 = 0; ja5 = 1; ja6 = 0; ja7 = 1;
    #1ja4 = 0; ja5 = 1; ja6 = 1; ja7 = 0;
    #1ja4 = 0; ja5 = 1; ja6 = 1; ja7 = 1;
    #1ja4 = 1; ja5 = 0; ja6 = 0; ja7 = 0;
    #1ja4 = 1; ja5 = 0; ja6 = 0; ja7 = 1;
    #1ja4 = 1; ja5 = 0; ja6 = 1; ja7 = 0;
    #1ja4 = 1; ja5 = 0; ja6 = 1; ja7 = 1;
    #1ja4 = 1; ja5 = 1; ja6 = 0; ja7 = 0;
    #1ja4 = 1; ja5 = 1; ja6 = 0; ja7 = 1;
    #1ja4 = 1; ja5 = 1; ja6 = 1; ja7 = 0;
    #1ja4 = 1; ja5 = 1; ja6 = 1; ja7 = 1;
    end

  initial begin //gatelevel3
    #24
    $display("\n\n");
    $display("A B C D | Y");
    $display("--------|---");
    $monitor("%b %b %b %b | %b", ja8, ja9, ja10, ja11, led2);
      ja8 = 0; ja9 = 0; ja10 = 0; ja11 = 0;
    #1ja8 = 0; ja9 = 0; ja10 = 0; ja11 = 1;
    #1ja8 = 0; ja9 = 0; ja10 = 1; ja11 = 0;
    #1ja8 = 0; ja9 = 0; ja10 = 1; ja11 = 1;
    #1ja8 = 0; ja9 = 1; ja10 = 0; ja11 = 0;
    #1ja8 = 0; ja9 = 1; ja10 = 0; ja11 = 1;
    #1ja8 = 0; ja9 = 1; ja10 = 1; ja11 = 0;
    #1ja8 = 0; ja9 = 1; ja10 = 1; ja11 = 1;
    #1ja8 = 1; ja9 = 0; ja10 = 0; ja11 = 0;
    #1ja8 = 1; ja9 = 0; ja10 = 0; ja11 = 1;
    #1ja8 = 1; ja9 = 0; ja10 = 1; ja11 = 0;
    #1ja8 = 1; ja9 = 0; ja10 = 1; ja11 = 1;
    #1ja8 = 1; ja9 = 1; ja10 = 0; ja11 = 0;
    #1ja8 = 1; ja9 = 1; ja10 = 0; ja11 = 1;
    #1ja8 = 1; ja9 = 1; ja10 = 1; ja11 = 0;
    #1ja8 = 1; ja9 = 1; ja10 = 1; ja11 = 1;
  end

  initial begin //gatelevel4
    #40
    $display("\n\n");
    $display("A B C | Y");
    $display("------|---");
    $monitor("%b %b %b | %b", ja12, ja13, ja14, led3);
      ja12 = 0 ; ja13 = 0; ja14 = 0;
    #1ja12 = 0 ; ja13 = 0; ja14 = 1;
    #1ja12 = 0 ; ja13 = 1; ja14 = 0;
    #1ja12 = 0 ; ja13 = 1; ja14 = 1;
    #1ja12 = 1 ; ja13 = 0; ja14 = 0;
    #1ja12 = 1 ; ja13 = 0; ja14 = 1;
    #1ja12 = 1 ; ja13 = 1; ja14 = 0;
    #1ja12 = 1 ; ja13 = 1; ja14 = 1;
  end

  initial begin //operador1
    #48
    $display("\n\n");
    $display("A B C | Y");
    $display("------|---");
    $monitor("%b %b %b | %b", ja15, ja16, ja17, led4);
      ja15 = 0; ja16 = 0; ja17 = 0;
    #1ja15 = 0; ja16 = 0; ja17 = 1;
    #1ja15 = 0; ja16 = 1; ja17 = 0;
    #1ja15 = 0; ja16 = 1; ja17 = 1;
    #1ja15 = 1; ja16 = 0; ja17 = 0;
    #1ja15 = 1; ja16 = 0; ja17 = 1;
    #1ja15 = 1; ja16 = 1; ja17 = 0;
    #1ja15 = 1; ja16 = 1; ja17 = 1;
  end

  initial begin //operator2
    #56
    $display("\n\n");
    $display("A B C D | Y");
    $display("--------|---");
    $monitor("%b %b %b %b | %b", ja18, ja19, ja20, ja21, led5);
      ja18 = 0; ja19 = 0; ja20 = 0; ja21 = 0;
    #1ja18 = 0; ja19 = 0; ja20 = 0; ja21 = 1;
    #1ja18 = 0; ja19 = 0; ja20 = 1; ja21 = 0;
    #1ja18 = 0; ja19 = 0; ja20 = 1; ja21 = 1;
    #1ja18 = 0; ja19 = 1; ja20 = 0; ja21 = 0;
    #1ja18 = 0; ja19 = 1; ja20 = 0; ja21 = 1;
    #1ja18 = 0; ja19 = 1; ja20 = 1; ja21 = 0;
    #1ja18 = 0; ja19 = 1; ja20 = 1; ja21 = 1;
    #1ja18 = 1; ja19 = 0; ja20 = 0; ja21 = 0;
    #1ja18 = 1; ja19 = 0; ja20 = 0; ja21 = 1;
    #1ja18 = 1; ja19 = 0; ja20 = 1; ja21 = 0;
    #1ja18 = 1; ja19 = 0; ja20 = 1; ja21 = 1;
    #1ja18 = 1; ja19 = 1; ja20 = 0; ja21 = 0;
    #1ja18 = 1; ja19 = 1; ja20 = 0; ja21 = 1;
    #1ja18 = 1; ja19 = 1; ja20 = 1; ja21 = 0;
    #1ja18 = 1; ja19 = 1; ja20 = 1; ja21 = 1;
  end

  initial begin //operator3
    #72
    $display("\n\n");
    $display("A B C D | Y");
    $display("--------|---");
    $monitor("%b %b %b %b | %b", jo1, jo2, jo3, jo4, led6);
      jo1 = 0; jo2 = 0; jo3 = 0; jo4 = 0;
    #1jo1 = 0; jo2 = 0; jo3 = 0; jo4 = 1;
    #1jo1 = 0; jo2 = 0; jo3 = 1; jo4 = 0;
    #1jo1 = 0; jo2 = 0; jo3 = 1; jo4 = 1;
    #1jo1 = 0; jo2 = 1; jo3 = 0; jo4 = 0;
    #1jo1 = 0; jo2 = 1; jo3 = 0; jo4 = 1;
    #1jo1 = 0; jo2 = 1; jo3 = 1; jo4 = 0;
    #1jo1 = 0; jo2 = 1; jo3 = 1; jo4 = 1;
    #1jo1 = 1; jo2 = 0; jo3 = 0; jo4 = 0;
    #1jo1 = 1; jo2 = 0; jo3 = 0; jo4 = 1;
    #1jo1 = 1; jo2 = 0; jo3 = 1; jo4 = 0;
    #1jo1 = 1; jo2 = 0; jo3 = 1; jo4 = 1;
    #1jo1 = 1; jo2 = 1; jo3 = 0; jo4 = 0;
    #1jo1 = 1; jo2 = 1; jo3 = 0; jo4 = 1;
    #1jo1 = 1; jo2 = 1; jo3 = 1; jo4 = 0;
    #1jo1 = 1; jo2 = 1; jo3 = 1; jo4 = 1;
  end

  initial begin //operador4
    #88
    $display("\n\n");
    $display("A B C | Y");
    $display("------|---");
    $monitor("%b %b %b | %b", jo5, jo6, jo7, led7);
      jo5 = 0; jo6 = 0; jo7 = 0;
    #1jo5 = 0; jo6 = 0; jo7 = 1;
    #1jo5 = 0; jo6 = 1; jo7 = 0;
    #1jo5 = 0; jo6 = 1; jo7 = 1;
    #1jo5 = 1; jo6 = 0; jo7 = 0;
    #1jo5 = 1; jo6 = 0; jo7 = 1;
    #1jo5 = 1; jo6 = 1; jo7 = 0;
    #1jo5 = 1; jo6 = 1; jo7 = 1;
  end

  initial
    #96$finish;

  initial begin
    $dumpfile("Gate_level_y_operadores_tb.vcd");
    $dumpvars(0, testbench);
  end

endmodule

Laboratorio 4/ejercicio 4/Gate_level_y_operadores_tb.vcd
$date
	Fri Aug 07 18:48:16 2020
$end
$version
	Icarus Verilog
$end
$timescale
	1ps
$end
$scope module testbench $end
$var wire 1 ! led7 $end
$var wire 1 " led6 $end
$var wire 1 # led5 $end
$var wire 1 $ led4 $end
$var wire 1 % led3 $end
$var wire 1 & led2 $end
$var wire 1 ' led1 $end
$var wire 1 ( led $end
$var reg 1 ) ja1 $end
$var reg 1 * ja10 $end
$var reg 1 + ja11 $end
$var reg 1 , ja12 $end
$var reg 1 - ja13 $end
$var reg 1 . ja14 $end
$var reg 1 / ja15 $end
$var reg 1 0 ja16 $end
$var reg 1 1 ja17 $end
$var reg 1 2 ja18 $end
$var reg 1 3 ja19 $end
$var reg 1 4 ja2 $end
$var reg 1 5 ja20 $end
$var reg 1 6 ja21 $end
$var reg 1 7 ja3 $end
$var reg 1 8 ja4 $end
$var reg 1 9 ja5 $end
$var reg 1 : ja6 $end
$var reg 1 ; ja7 $end
$var reg 1 < ja8 $end
$var reg 1 = ja9 $end
$var reg 1 > jo1 $end
$var reg 1 ? jo2 $end
$var reg 1 @ jo3 $end
$var reg 1 A jo4 $end
$var reg 1 B jo5 $end
$var reg 1 C jo6 $end
$var reg 1 D jo7 $end
$scope module G $end
$var wire 1 ) A $end
$var wire 1 4 B $end
$var wire 1 7 C $end
$var wire 1 ( out $end
$upscope $end
$scope module G1 $end
$var wire 1 8 A $end
$var wire 1 9 B $end
$var wire 1 : C $end
$var wire 1 ; D $end
$var wire 1 E a1 $end
$var wire 1 F a2 $end
$var wire 1 G a3 $end
$var wire 1 H a4 $end
$var wire 1 I b1 $end
$var wire 1 J b2 $end
$var wire 1 K b3 $end
$var wire 1 L b4 $end
$var wire 1 M b5 $end
$var wire 1 N b6 $end
$var wire 1 O b7 $end
$var wire 1 P b8 $end
$var wire 1 ' out $end
$upscope $end
$scope module G2 $end
$var wire 1 < A $end
$var wire 1 = B $end
$var wire 1 * C $end
$var wire 1 + D $end
$var wire 1 Q c1 $end
$var wire 1 R c2 $end
$var wire 1 S c3 $end
$var wire 1 T c4 $end
$var wire 1 U d1 $end
$var wire 1 V d2 $end
$var wire 1 W d3 $end
$var wire 1 X d4 $end
$var wire 1 & out $end
$upscope $end
$scope module G3 $end
$var wire 1 , A $end
$var wire 1 - B $end
$var wire 1 . C $end
$var wire 1 Y e1 $end
$var wire 1 % out $end
$upscope $end
$scope module OP1 $end
$var wire 1 / A $end
$var wire 1 0 B $end
$var wire 1 1 C $end
$var wire 1 $ out $end
$upscope $end
$scope module OP2 $end
$var wire 1 2 A $end
$var wire 1 3 B $end
$var wire 1 5 C $end
$var wire 1 6 D $end
$var wire 1 # out $end
$upscope $end
$scope module OP3 $end
$var wire 1 > A $end
$var wire 1 ? B $end
$var wire 1 @ C $end
$var wire 1 A D $end
$var wire 1 " out $end
$upscope $end
$scope module OP4 $end
$var wire 1 B A $end
$var wire 1 C B $end
$var wire 1 D C $end
$var wire 1 ! out $end
$upscope $end
$upscope $end
$enddefinitions $end
#0
$dumpvars
xY
xX
xW
xV
xU
xT
xS
xR
xQ
xP
xO
xN
xM
xL
xK
xJ
xI
xH
xG
xF
xE
xD
xC
xB
xA
x@
x?
x>
x=
x<
x;
x:
x9
x8
07
x6
x5
04
x3
x2
x1
x0
x/
x.
x-
x,
x+
x*
0)
1(
x'
x&
x%
x$
x#
x"
x!
$end
#1
17
#2
0(
07
14
#3
17
#4
1(
07
04
1)
#5
17
#6
0(
07
14
#7
17
#8
1'
1I
1H
1G
0J
1F
0K
0L
1E
0M
0N
0O
0P
0;
0:
09
08
#9
0'
0I
0H
1;
#10
1H
0G
0;
1:
#11
1'
0H
1J
1;
#12
0'
1H
1G
0J
0F
0;
0:
19
#13
1'
0H
1K
1;
#14
1'
1L
1H
0K
0G
0;
1:
#15
0'
0L
0H
1;
#16
1H
1G
1F
0E
0;
0:
09
18
#17
1'
0H
1O
1;
#18
1'
1P
1H
0O
0G
0;
1:
#19
0'
0P
0H
1;
#20
1'
1M
1H
1G
0F
0;
0:
19
#21
0'
0M
0H
1;
#22
1H
0G
0;
1:
#23
1'
0H
1N
1;
#24
1&
1X
1T
1S
1R
1Q
0U
0V
0W
0+
0*
0=
0<
#25
0&
0X
0T
1+
#26
1T
0S
0+
1*
#27
0T
1+
#28
1T
1S
0R
0+
0*
1=
#29
0T
1+
#30
1T
0S
0+
1*
#31
0T
1+
#32
1&
1V
1U
1W
1X
1T
1S
1R
0Q
0+
0*
0=
1<
#33
0V
0X
0T
1+
#34
1V
0U
1T
0S
0+
1*
#35
0V
0T
1+
#36
1V
1U
0W
1T
1S
0R
0+
0*
1=
#37
0V
0T
1+
#38
1V
0U
1T
0S
0+
1*
#39
0&
0V
0T
1+
#40
1%
1Y
0.
0-
0,
#41
1.
#42
0%
0Y
0.
1-
#43
1%
1.
#44
1Y
0.
0-
1,
#45
1.
#46
0%
0Y
0.
1-
#47
1%
1.
#48
1$
01
00
0/
#49
0$
11
#50
1$
01
10
#51
0$
11
#52
1$
01
00
1/
#53
11
#54
0$
01
10
#55
1$
11
#56
0#
06
05
03
02
#57
16
#58
06
15
#59
16
#60
06
05
13
#61
1#
16
#62
0#
06
15
#63
1#
16
#64
1#
06
05
03
12
#65
0#
16
#66
1#
06
15
#67
16
#68
1#
06
05
13
#69
16
#70
06
15
#71
16
#72
0"
0A
0@
0?
0>
#73
1"
1A
#74
0"
0A
1@
#75
1A
#76
1"
0A
0@
1?
#77
1A
#78
0A
1@
#79
1A
#80
0"
0A
0@
0?
1>
#81
1"
1A
#82
0"
0A
1@
#83
1"
1A
#84
0A
0@
1?
#85
1A
#86
0A
1@
#87
1A
#88
1!
0D
0C
0B
#89
0!
1D
#90
1!
0D
1C
#91
1D
#92
0!
0D
0C
1B
#93
1D
#94
1!
0D
1C
#95
1D
