Laboratorio 3/01-TABLA-SOP/TABLA1_SOP.v
module TABLA1_SOP();


reg A, B, C;
wire a1, a2, a3, b1, b2, b3, b4, b5, out;

not ja1(a1, A);
not ja2(a2, B);
not ja3(a3, C);
and ja4(b1, a1, a2, a3);
and ja5(b2, a1, B, a3);
and ja6(b3, A, a2, a3);
and ja7(b4, A, a2, C);
and ja8(b5, A, B, C);
or  ja9(out, b1, b2, b3, b4, b5);

initial begin
  $display("A B C | Y");
  $monitor("%b %b %b | %b", A, B, C, out);
  A = 0; B = 0; C = 0;
  #1 C = 1;
  #1 B = 1; C = 0;
  #1 C = 1;
  #1 A = 1; B = 0; C = 0;
  #1 C = 1;
  #1 B = 1; C = 0;
  #1 C = 1;
  #1 $finish;
end

initial
    begin
      $dumpfile("TABLA1_SOP_tb.vcd");
      $dumpvars(0, TABLA1_SOP);
    end
endmodule

//se utilizo apio sim

Laboratorio 3/01-TABLA-SOP/TABLA1_SOP_tb.vcd
$date
	Sat Aug 01 15:45:47 2020
$end
$version
	Icarus Verilog
$end
$timescale
	1ps
$end
$scope module TABLA1_SOP $end
$var wire 1 ! a1 $end
$var wire 1 " a2 $end
$var wire 1 # a3 $end
$var wire 1 $ b1 $end
$var wire 1 % b2 $end
$var wire 1 & b3 $end
$var wire 1 ' b4 $end
$var wire 1 ( b5 $end
$var wire 1 ) out $end
$var reg 1 * A $end
$var reg 1 + B $end
$var reg 1 , C $end
$upscope $end
$enddefinitions $end
#0
$dumpvars
0,
0+
0*
1)
0(
0'
0&
0%
1$
1#
1"
1!
$end
#1
0)
0$
0#
1,
#2
1)
1%
1#
0"
0,
1+
#3
0)
0%
0#
1,
#4
1)
1&
1#
1"
0!
0,
0+
1*
#5
0&
1'
0#
1,
#6
0)
0'
1#
0"
0,
1+
#7
1)
1(
0#
1,
