laboratorio 9/Ejercicio 1/FLIP-FLOP-D-4/FLIPFLOP4.v
module flip_flop(input clk, reset,En, D, output reg Q);
  always @ (posedge clk or posedge reset)begin
    if (reset)
      Q <= 1'b0;
    else if (En)
      Q <= D;
  end
endmodule

module flip_flop_4(input clk, reset, En, input wire [3:0]D, output[3:0]Q);

  flip_flop a(clk, reset, En, D[3], Q[3]);
  flip_flop b1(clk, reset, En, D[2], Q[2]);
  flip_flop b2(clk, reset, En, D[1], Q[1]);
  flip_flop b3(clk, reset, En, D[0], Q[0]);

endmodule

laboratorio 9/Ejercicio 1/FLIP-FLOP-D-4/FLIPFLOP4_tb.v
module testbench();

  reg clk, reset, En;
  reg [3:0]D;
  wire [3:0]Q;

  flip_flop_4 c(clk, reset, En, D, Q);

  always
    begin
    #1 clk = ~clk;
  end

    initial begin
      #1
      $display("|clk reset En D | Q |");
      $display("-------------------");
      $monitor("|%b   %b   %b  %b | %b |",clk,reset, En, D, Q);
         clk = 0; reset = 0; En = 0; D = 4'b0000;
      #1 reset = 1;
      #1 reset = 0; En = 1;
      #1 D = 4'b0001;
      #1 D = 4'b0001;
      #1 D = 4'b0001;
      #1 D = 4'b1010;
      #1 D = 4'b1010; En = 0;
      #1 D = 4'b1010;
      #1 D = 4'b0010;
      #1 D = 4'b0010;
      #1 D = 4'b0010;
      #1 D = 4'b0100; En = 1;
      #1 D = 4'b0100;
      #1 D = 4'b1111;
      #1 D = 4'b1111;
      #1 D = 4'b1111;
      #1 D = 4'b1111;

    end

      initial
        #18 $finish;

      initial begin
        $dumpfile("FLIPFLOP4_tb.vcd");
        $dumpvars(0, testbench);
      end

endmodule //

laboratorio 9/Ejercicio 1/FLIP-FLOP-D-4/FLIPFLOP4_tb.vcd
$date
	Sat Oct 31 03:54:25 2020
$end
$version
	Icarus Verilog
$end
$timescale
	1ps
$end
$scope module testbench $end
$var wire 4 ! Q [3:0] $end
$var reg 4 " D [3:0] $end
$var reg 1 # En $end
$var reg 1 $ clk $end
$var reg 1 % reset $end
$scope module c $end
$var wire 4 & D [3:0] $end
$var wire 1 # En $end
$var wire 1 $ clk $end
$var wire 1 % reset $end
$var wire 4 ' Q [3:0] $end
$scope module a $end
$var wire 1 ( D $end
$var wire 1 # En $end
$var wire 1 $ clk $end
$var wire 1 % reset $end
$var reg 1 ) Q $end
$upscope $end
$scope module b1 $end
$var wire 1 * D $end
$var wire 1 # En $end
$var wire 1 $ clk $end
$var wire 1 % reset $end
$var reg 1 + Q $end
$upscope $end
$scope module b2 $end
$var wire 1 , D $end
$var wire 1 # En $end
$var wire 1 $ clk $end
$var wire 1 % reset $end
$var reg 1 - Q $end
$upscope $end
$scope module b3 $end
$var wire 1 . D $end
$var wire 1 # En $end
$var wire 1 $ clk $end
$var wire 1 % reset $end
$var reg 1 / Q $end
$upscope $end
$upscope $end
$upscope $end
$enddefinitions $end
#0
$dumpvars
x/
x.
x-
x,
x+
x*
x)
x(
bx '
bx &
x%
x$
x#
bx "
bx !
$end
#1
0(
0*
0,
0.
b0 "
b0 &
0#
0%
0$
#2
0)
0+
0-
b0 !
b0 '
0/
1%
1$
#3
1#
0%
0$
#4
1.
b1 "
b1 &
1$
#5
0$
#6
b1 !
b1 '
1/
1$
#7
1(
1,
0.
b1010 "
b1010 &
0$
#8
0#
1$
#9
0$
#10
0(
b10 "
b10 &
1$
#11
0$
#12
1$
#13
1*
0,
1#
b100 "
b100 &
0$
#14
1+
b100 !
b100 '
0/
1$
#15
1(
1,
1.
b1111 "
b1111 &
0$
#16
1/
1-
b1111 !
b1111 '
1)
1$
